Workbook

Sheet Index
A1: Nessovo HumanOS Work Intelligence — Programme Workbook
A2: Complete HumanOS Work Intelligence blueprint and repository assessment. Start with START HERE and AI Coding Handoff; use Index as the complete navigation and source-of-truth map.
A4: Workbook section | B4: Purpose | C4: Primary users | D4: Stage | E4: Current state | F4: Approval state | G4: Next action | H4: Notes
A5: Foundation Dashboard | B5: Stage 0–1 readiness, blockers and decisions. | C5: Leadership | D5: 0–1 | E5: Complete | F5: Gates pending | G5: Resolve formal Stage 0–1 approvals.
A6: Stage 2-3 Dashboard | B6: Stage 2 and 3 readiness, backlog maturity, sources and interpretation. | C6: Leadership/Programme | D6: 2–3 | E6: Complete | F6: Gates pending | G6: Review Stage 2–3 gate items.
A7: Master Prompts | B7: Applied and next-stage prompts including Stages 4 and 5. | C7: Programme/Product/Architecture | D7: 0–5 | E7: Updated | F7: N/A | G7: Use prompts for next stages.
A8: Executive Charter | B8: Concise executive decision summary. | C8: Leadership | D8: 0–3 | E8: Updated | F8: Leadership approval pending | G8: Use with dashboards.
A9: Delivery Stages | B9: 13-stage roadmap and current stage statuses. | C9: Programme | D9: All | E9: Updated | F9: Pending leadership approval | G9: Mobilise Stage 4–5 after gates.
A10: Product Charter v1 | B10: Strategic purpose, principles and scope. | C10: CEO/CTO/Product | D10: 0 | E10: Draft complete | F10: Stage 0 approval pending | G10: Approve or condition.
A11: Purpose Policy Matrix | B11: Purpose, necessity and minimisation by data category. | C11: DPO/Legal/Security | D11: 0 | E11: Draft complete | F11: DPIA/legal approval pending | G11: Review before capture.
A12: Stakeholder RACI | B12: Accountability matrix. | C12: Programme/Leadership | D12: 0–1 | E12: Draft complete | F12: Named owners pending | G12: Replace roles with names.
A13: Market Landscape | B13: Commercial category research. | C13: Product/Strategy | D13: 1 | E13: Updated | F13: Review pending | G13: Maintain quarterly.
A14: GitHub OSS Scan | B14: Open-source/source-available reference scan. | C14: Architecture/Legal/Security | D14: 1 | E14: Updated | F14: Licence approval pending | G14: Complete legal review before code reuse.
A15: Gap Matrix | B15: Competitive gap and proprietary-core matrix. | C15: Product/Strategy | D15: 1 | E15: Updated | F15: Leadership review pending | G15: Approve differentiation boundary.
A16: Build Buy Decisions | B16: Build/buy/integrate/defer matrix. | C16: CTO/Product/Legal | D16: 1 | E16: Draft complete | F16: Procurement/legal review pending | G16: Approve component decisions.
... A257: Validation Summary | B257: Workbook formula, validation, index and integrity audit. | C257: Programme/QA | D257: Handoff | E257: Current | F257: N/A | G257: Review before distribution.

Sheet Executive Charter
A1: Executive Charter — Foundation Decision Summary
A2: Concise leadership view. The detailed charter is maintained in Product Charter v1; governance and architecture approvals remain formally pending.
A4: Area | B4: Foundation decision | C4: Current state | D4: Required leadership action
A5: Company | B5: Nessovo | C5: Confirmed | D5: Use as canonical company name.
A6: Platform placement | B6: HumanOS Work Intelligence is a HumanOS module, reusing foundation microservices and supporting future business verticals. | C6: Draft complete | D6: Approve platform placement.
A7: Product definition | B7: Task-aware human-and-AI work intelligence that reconstructs evidence, assures outcomes, develops capability and improves HumanOS skills. | C7: Draft complete | D7: Approve charter and working product name.
A8: Strategic position | B8: Task execution assurance, capability development and human–AI work governance—not activity-volume surveillance. | C8: Draft complete | D8: Approve market position.
A9: Initial vertical | B9: AI-assisted software development on company-managed Windows and macOS devices. | C9: Draft complete | D9: Approve pilot scope and cohort.
A10: Core proprietary capabilities | B10: Evidence/provenance graph; Task Assurance; Capability Graph; Growth Coach; governed Skill Forge. | C10: Draft complete | D10: Approve build focus.
A11: Commodity/reference capabilities | B11: Application/window/browser activity, event streaming, object storage, operational observability and standard OS capture primitives. | C11: Draft complete | D11: Approve build/buy/reference strategy.
A12: Employee value | B12: Fair work attribution, blocker explanation, transparent evidence, correction rights, contextual coaching and skill progression. | C12: Draft complete | D12: Require measurable employee benefit in pilot.
A13: Employer value | B13: Evidence-linked task outcomes, quality, blockers, capability gaps, training effectiveness and safer AI-agent use. | C13: Draft complete | D13: Require exception-led reporting and human judgement.
A14: Governance boundary | B14: No covert general monitoring, emotion/personality inference, click/keystroke productivity scoring or solely automated consequential employment decisions. | C14: Draft complete | D14: Approve prohibited uses and policy enforcement.
A15: Employee rights | B15: Visible monitoring, own evidence access, correction, explanation, dispute and meaningful human review. | C15: Draft complete | D15: Approve operational rights workflow.
... A22: Next mobilisation | B22: Stage 2 Role/Task/Capability Ontology and Stage 3 Device Agent Foundation. | C22: Prompts ready | D22: Mobilise only under gate conditions and named ownership.

Sheet Market Landscape
A1: Market Landscape — Commercial and Category References
A2: No single reviewed platform provides Nessovo's complete combination. The strategic gap is the integrated evidence → task assurance → capability development → governed self-improvement loop.
A4: Vendor / system | B4: Category | C4: Proven market capability | D4: Relevant lesson | E4: Limit relative to Nessovo target | F4: Nessovo action | G4: Strategic relevance | H4: Source URL | I4: Research note
A5: Teramind | B5: Employee monitoring / insider risk | C5: Screen recording/playback, keystrokes, applications, websites, active/idle and behavioural controls. | D5: Comprehensive desktop monitoring is commercially established. | E5: Primarily observes and governs activity; does not provide evidence-linked task contracts, capability progression and Skill Forge. | F5: Benchmark control coverage; do not use as product core unless later enterprise connector is justified. | G5: High | H5: https://www.teramind.co/solutions/employee-monitoring/ | I5: Closest commercial baseline for raw monitoring.
A6: ActivTrak | B6: Workforce analytics / AI adoption | C6: Application and website analytics, work patterns, productivity/capacity views, AI usage and coaching-oriented insights. | D6: Management demand is moving from time tracking to workforce and AI-use intelligence. | E6: Aggregate behavioural analytics rather than exact causal task reconstruction and technical-quality assurance. | F6: Benchmark reporting and manager experience. | G6: High | H6: https://support.activtrak.com/hc/en-us/articles/50125731483675-AI-Insights-Add-on | I6: Relevant to reporting and adoption metrics.
A7: UiPath Task Mining / Task Capture | B7: Task mining / automation discovery | C7: Desktop screenshots, clicks/keyboard actions, UI elements, process sequences and automation opportunity discovery. | D7: Action-level capture and workflow reconstruction are proven enterprise patterns. | E7: Optimised for process discovery/automation rather than individual task-outcome assurance and capability development. | F7: Learn capture/review patterns; consider future process-platform integration. | G7: High | H7: https://docs.uipath.com/task-capture/standalone/2021.10/user-guide/capture-settings | I7: Strong evidence that click + screenshot + UI context is viable.
A8: ABBYY Timeline Task Mining | B8: Task/process intelligence | C8: Screen snapshots, buttons clicked, text entered, application usage and task association. | D8: Task definitions can organise raw user actions into analysable sequences. | E8: Does not provide the complete role-claim, capability, real-time coaching and self-improvement model. | F8: Learn task-segmentation and process-variant concepts. | G8: High | H8: https://help.abbyy.com/en-us/timeline/6/user_guide/task-mining
A9: Soroco Scout | B9: Work graph / process intelligence | C9: Maps team-machine interactions, process variants, workarounds, effort leakage and automation opportunities. | D9: A work-graph framing is strategically close to Nessovo's evidence/provenance graph. | E9: Generally team/process-oriented and privacy-minimised rather than exact individual task assurance and training. | F9: Benchmark graph terminology and enterprise process use cases. | G9: Medium | H9: https://soroco.com/
A10: Workfellow | B10: Process intelligence / task mining | C10: Combines process and task mining to locate workflow friction and automation potential. | D10: There is demand for understanding how work actually flows across systems. | E10: Limited public evidence of exact text, technical outcome validation or longitudinal capability development. | F10: Watch and compare process-intelligence partnerships. | G10: Medium | H10: https://www.workfellow.ai/
A11: Microsoft Power Automate AI Recorder | B11: Record / replay / RPA | C11: Records screen, voice, mouse and keyboard demonstrations and converts them into desktop automations. | D11: A demonstrated successful workflow can become a reusable procedure. | E11: Creates automation, not a continuous task, capability and employee-development operating system. | F11: Adopt demonstration-to-skill mental model; do not depend on it for core capture. | G11: Medium | H11: https://learn.microsoft.com/en-us/power-automate/desktop-flows/create-flow-using-ai-recorder
A12: OpenAI Codex Hooks | B12: AI-agent lifecycle instrumentation | C12: Lifecycle hooks around prompts, tools, permissions, session start/stop and validations. | D12: Official semantic hooks are more accurate than screen-only inference for agent activity. | E12: Provider-specific and limited to instrumented Codex activity. | F12: Integrate through a provider-normalising AI Adapter Hub. | G12: High | H12: https://developers.openai.com/codex/hooks | I12: Core provenance input.
A13: OpenAI Record & Replay | B13: Workflow demonstration to reusable skill | C13: Converts a demonstrated stable workflow into a reusable skill with inputs, steps and verification. | D13: Strong model for turning real work into governed reusable skills. | E13: Not a continuous employee work-intelligence platform and availability/feature scope may vary. | F13: Learn for Skill Forge; keep HumanOS implementation provider-neutral. | G13: Medium | H13: https://developers.openai.com/codex/record-and-replay
A14: LinearB | B14: Developer productivity and AI-work governance | C14: Engineering workflow metrics, bottleneck analysis, AI activity detection, workflow automation, team coaching and business alignment. | D14: Developer intelligence increasingly combines AI adoption, workflow and outcome signals. | E14: Centred on SDLC/tool data and delivery metrics rather than universal desktop evidence, job capability claims and cross-vertical learning. | F14: Benchmark technical-manager experience and integrate Git/SDLC data where useful. | G14: High | H14: https://linearb.io/platform/ai-developer-productivity-insights | I14: Strong adjacent competitor for software-development vertical.
A15: Jellyfish | B15: Engineering intelligence / AI-SDLC | C15: Combines developer-tool, allocation, delivery, AI usage, cost, bottleneck and developer-experience signals. | D15: Task/project, PR and AI-use data can be tied to business outcomes without manual time tracking. | E15: Does not publicly position as universal endpoint reconstruction, exact human/agent causality or role capability verification. | F15: Benchmark outcome-based engineering reporting and AI ROI. | G15: High | H15: https://jellyfish.co/ | I15: Strong adjacent competitor.
A16: GitClear | B16: Code quality and developer analytics | C16: Repository-level code activity, AI-code impact, code-quality research and review analytics. | D16: Code-change quality and attribution are more useful than raw line-count metrics. | E16: Repository scope cannot explain all desktop work, requirements, blockers or capability context. | F16: Consider future connector/benchmark; retain Nessovo task/provenance core. | G16: Medium | H16: https://www.gitclear.com/
A17: TechWolf | B17: Skills/work intelligence | C17: Continuously infers skills from actual work signals and connects skills, work and market intelligence. | D17: Self-reported skills are insufficient; dynamic work evidence is a validated market need. | E17: Focuses on workforce skills intelligence rather than exact task execution, raw evidence and real-time technical coaching. | F17: Benchmark skills ontology, HR integration and evidence transparency; build Nessovo Capability Graph. | G17: High | H17: https://www.techwolf.ai/product/skills-intelligence | I17: Directly relevant to role-claim and capability goals.
A18: Eightfold | B18: Talent and work intelligence | C18: Models skills, capabilities, aspirations and work signals for hiring, development, project staffing and career recommendations. | D18: Live work signals are entering talent intelligence and career development. | E18: Broader HR/talent platform; public material does not demonstrate Nessovo's exact endpoint/task-evidence and challenge model. | F18: Benchmark role readiness, employee growth and talent-market integration. | G18: High | H18: https://eightfold.ai/products/
A19: Gloat | B19: Workforce graph / agentic HR | C19: Dynamic skills ontology, workforce graph, task-role mapping, work orchestration, audit trails and agentic HR actions. | D19: Workforce graphs, governed agent actions and task-level human–AI orchestration validate parts of Nessovo's direction. | E19: HR-system and workforce orchestration focus rather than complete endpoint evidence and task-quality reconstruction. | F19: Benchmark workforce graph, employee experience and explainable agent action. | G19: High | H19: https://gloat.com/platform/workforce-graph/ | I19: Important strategic adjacent platform.
A20: Degreed | B20: Learning, coaching and skills development | C20: AI-powered learning, coaching, roleplay, skill review, pathways and behaviour-change-oriented development. | D20: Training must be personalised and measured through behaviour/application, not content completion alone. | E20: Does not provide universal work observation, task assurance or causal provenance. | F20: Integrate/buy content selectively; build the evidence-to-learning effectiveness loop. | G20: High | H20: https://degreed.com/experience/artificial-intelligence/
A21: OpenTelemetry GenAI semantic conventions | B21: Open standard / AI observability | C21: Common attributes and events for model, agent, tool and provider telemetry. | D21: Standards reduce provider lock-in and improve cross-agent correlation. | E21: Operational conventions do not define employee, task, capability, evidence or employment governance semantics. | F21: Adopt operational conventions and extend with Nessovo domain contracts; keep raw evidence separate. | G21: High | H21: https://opentelemetry.io/docs/specs/semconv/registry/attributes/gen-ai/
A22: Nessovo HumanOS Work Intelligence | B22: Task assurance / capability development / organisational learning | C22: Target combination: universal evidence, task contracts, human/AI provenance, outcome verification, capability graph, coaching, employee challenge and governed Skill Forge. | D22: The product opportunity is integration and semantics, not invention of every capture primitive. | E22: Requires higher accuracy, governance, endpoint security and cross-domain architecture than any single adjacent category. | F22: Build proprietary core; integrate commodity standards and tools. | G22: Critical | H22: Internal product definition | I22: Strategic target.

Sheet GitHub OSS Scan
A1: GitHub / Open-Source and Source-Available Scan
A2: Repository research for architecture and implementation references. Licence and security review are mandatory before code incorporation or distribution.
A4: Repository | B4: Category | C4: Useful architecture / pattern | D4: Maturity signal | E4: Limit / risk | F4: Verified licence posture | G4: Recommended stance | H4: Likely stage | I4: Source URL | J4: Due-diligence action
A5: screenpipe/screenpipe | B5: Local screen/audio/activity memory | C5: Event-driven visual capture, accessibility-first text, OCR fallback, keyboard/app switches, local storage/search and AI pipes. | D5: Large active source-available project with Windows/macOS/Linux support claims and desktop product. | E5: Commercial licence for commercial use; broad capture and local AI design still require independent security/performance review. | F5: Source-available; repository states personal/non-commercial use and commercial licence requirement. | G5: Study and benchmark; negotiate licence only if strategically justified; do not make it the proprietary core by default. | H5: 3–5 | I5: https://github.com/screenpipe/screenpipe | J5: Legal review; architecture/performance benchmark; supply-chain review.
A6: ActivityWatch/activitywatch | B6: Privacy-first activity tracking | C6: Watcher/server architecture for active window, browser tab and AFK events; local data ownership and extensibility. | D6: Long-running cross-platform project with modular watcher ecosystem. | E6: Lower fidelity; no task assurance, screenshots or exact semantic provenance. MPL file-level obligations matter if code is modified/distributed. | F6: MPL-2.0 verified in repository licence. | G6: Use architecture ideas and possibly protocol-level compatibility; code reuse only after legal decision. | H6: 3–5 | I6: https://github.com/ActivityWatch/activitywatch | J6: Map relevant watcher modules and MPL obligations.
A7: ActivityWatch/aw-watcher-window | B7: Active-window watcher | C7: Small focused watcher producing foreground-window events to a local server. | D7: Mature component in ActivityWatch ecosystem. | E7: Platform-specific behaviour and title sensitivity. | F7: Repository-family licence should be verified per component. | G7: Reference for event semantics and tests. | H7: 3–5 | I7: https://github.com/ActivityWatch/aw-watcher-window | J7: Inspect OS implementations and redaction options.
A8: ActivityWatch/aw-watcher-web | B8: Browser watcher | C8: Browser-extension watcher for active tab/title/URL events. | D8: Mature ActivityWatch companion project. | E8: Browser permissions and sensitive URL/title collection. | F8: Repository-family licence should be verified per component. | G8: Reference for minimal browser adapter. | H8: 6 | I8: https://github.com/ActivityWatch/aw-watcher-web | J8: Inspect extension permissions and native communication.
A9: OpenAdaptAI/openadapt-desktop | B9: Desktop recording / human teaching | C9: Capture/review UI, local engine, Tauri/React shell, Python sidecar and bridge to record/compile/replay/teach. | D9: Repository explicitly labels the desktop surface experimental and not a supported production release. | E9: End-to-end boundaries are mocked; no validated production installer; flow engine is separate. | F9: MIT verified by repository README/licence. | G9: Study architecture, consent/review and teaching concepts; do not treat as deployable foundation. | H9: 3,11 | I9: https://github.com/OpenAdaptAI/openadapt-desktop | J9: Inspect capture/privacy subprojects and implementation maturity.
A10: OpenAdaptAI/openadapt-flow | B10: Deterministic workflow compiler/runtime | C10: Record → compile → lint/certify → replay → halt/repair/teach lifecycle. | D10: Canonical OpenAdapt workflow engine according to desktop README. | E10: GUI replay is a future Skill Forge capability, not initial work assurance; safety scope is significant. | F10: Verify repository licence before reuse. | G10: Reference for governed workflow compilation and verification. | H10: 11+ | I10: https://github.com/OpenAdaptAI/openadapt-flow | J10: Licence/security review and isolated future spike.
A11: OpenAdaptAI/openadapt-privacy | B11: PII detection and redaction | C11: Experimental privacy component associated with OpenAdapt capture. | D11: Experimental supporting project. | E11: PII/secret redaction quality must be independently evaluated against Nessovo data. | F11: Verify repository licence and model licences. | G11: Benchmark only; Nessovo needs its own edge policy and test corpus. | H11: 3–5 | I11: https://github.com/OpenAdaptAI/openadapt-privacy | J11: Evaluate false negatives and model provenance.
A12: thedotmack/claude-mem | B12: AI-agent persistent memory | C12: Lifecycle hooks, local worker, asynchronous observation compression, SQLite/FTS5, vector search and real-time viewer. | D12: Large active project with documented architecture and multi-environment support. | E12: Claude-centric; memory content and provider dependencies require HumanOS tenant/policy redesign. | F12: Apache-2.0 verified in repository metadata/readme. | G12: Adapt architecture pattern, not necessarily code; integrate official agent hooks into HumanOS memory/evidence. | H12: 6,11 | I12: https://github.com/thedotmack/claude-mem | J12: Security review, provider abstraction and licence provenance.
A13: rebelytics/one-skill-to-rule-them-all | B13: Continuous skill improvement methodology | C13: Structured observations of corrections/gaps, cross-cutting principles, periodic review and human-approved skill changes. | D13: Methodology reports extensive real-world use; compact repository. | E13: Not a recorder or runtime; file-based process is not sufficient for multi-tenant HumanOS. | F13: CC BY 4.0 stated in repository README. | G13: Adapt methodology with attribution into governed Skill Forge. | H13: 11 | I13: https://github.com/rebelytics/one-skill-to-rule-them-all | J13: Preserve attribution; separate confidential/internal skill content.
A14: wakatime/wakatime-cli | B14: Developer activity telemetry | C14: Editor/CLI heartbeat model, project/language metadata and broad plugin ecosystem. | D14: Active Go CLI used by WakaTime integrations. | E14: Developer-tool-only; heartbeat/time telemetry cannot establish task quality or capability. | F14: BSD 3-Clause verified in repository licence. | G14: Reference or optional connector for supported editor metadata. | H14: 6 | I14: https://github.com/wakatime/wakatime-cli | J14: Review privacy and data fields before connector design.
A15: open-telemetry/semantic-conventions | B15: Operational observability standard | C15: Cross-language semantic conventions for traces, metrics and logs. | D15: CNCF/OpenTelemetry standard ecosystem. | E15: Operational telemetry is not the employee evidence store; sensitive content may leak if misconfigured. | F15: Apache-2.0 ecosystem; verify repository licence at incorporation. | G15: Adopt conventions through existing HumanOS observability. | H15: 3+ | I15: https://github.com/open-telemetry/semantic-conventions | J15: Define content policy and correlation IDs.
... A20: temporalio/sdk-python | B20: Durable workflow SDK | C20: Python workflow/activity support for long-running AI pipelines. | D20: Mature Temporal ecosystem. | E20: Cross-language workflow ownership and duplicate orchestration complexity. | F20: MIT in repository ecosystem; verify before use. | G20: Reference only; Python evaluators should remain workers behind HumanOS orchestration initially. | H20: 1,7+ | I20: https://github.com/temporalio/sdk-python | J20: Use only after architecture decision.

Sheet Gap Matrix
A1: Competitive Gap and Proprietary-Core Matrix
A2: The market provides strong components. Nessovo's defensible product is the governed integration of evidence, task outcomes, provenance, capability development and organisational learning.
A4: Capability | B4: Employee monitoring | C4: Task/process mining | D4: Developer intelligence | E4: Skills/talent intelligence | F4: AI memory / record-replay | G4: Nessovo target | H4: Proprietary importance | I4: MVP / stage | J4: Differentiation and design note
A5: Managed-device session and policy control | B5: Medium | C5: Low | D5: Low | E5: Low | F5: Low | G5: Strong | H5: Medium | I5: 3 | J5: Visible, task/hour/policy-scoped device control is foundational to trust.
A6: Application/window/browser context | B6: Strong | C6: Medium | D6: Medium | E6: Low | F6: Low | G6: Strong | H6: Low | I6: 5–6 | J6: Commodity evidence; use minimum necessary fields and employee visibility.
A7: Event-driven visual-state capture | B7: Strong | C7: Strong | D7: Low | E7: Low | F7: Medium | G7: Strong | H7: Medium | I7: 5 | J7: Changed-state graph, secure exclusions and edge redaction are the value beyond screenshots.
A8: Keyboard/input provenance and resulting text reconciliation | B8: Strong raw keys | C8: Medium | D8: Low/Medium | E8: Low | F8: Medium in agent tools | G8: Controlled strong | H8: High | I8: 5–6 | J8: Distinguish typed, pasted, autocomplete, agent-generated and system-generated changes.
A9: Files, Git, terminal, build and test semantics | B9: Low | C9: Low | D9: Strong | E9: Low | F9: Medium | G9: Strong | H9: Medium | I9: 6 | J9: Prefer authoritative artefacts/results over visual inference.
A10: AI-agent lifecycle and tool instrumentation | B10: Emerging | C10: Low | D10: Strong/emerging | E10: Medium | F10: Strong | G10: Strong | H10: High | I10: 6 | J10: Provider-neutral Adapter Hub plus official hooks and model/skill versioning.
A11: Human / AI / automation causal provenance | B11: Low | C11: Low | D11: Medium | E11: Low | F11: Medium | G11: Strong | H11: Very High | I11: 6–7 | J11: Fair credit, automated-wait classification and agent supervision depend on this.
A12: Task Execution Contract | B12: Low | C12: Medium task definitions | D12: Medium ticket links | E12: Low | F12: Low | G12: Strong | H12: Very High | I12: 2 | J12: Transforms vague tasks into objective, versioned criteria, evidence and quality gates.
A13: Task alignment and supporting-work classification | B13: Medium | C13: Strong for process patterns | D13: Medium | E13: Low | F13: Low | G13: Strong | H13: High | I13: 7 | J13: Must support multiple assigned tasks, research, collaboration and environmental blockers.
A14: Acceptance-criteria and quality verification | B14: Low | C14: Low | D14: Medium | E14: Low | F14: Medium verification in replay | G14: Strong | H14: Very High | I14: 7 | J14: Activity is not completion; deterministic evidence and expert review are essential.
A15: Evidence hierarchy, confidence and alternatives | B15: Low | C15: Low | D15: Medium | E15: Medium | F15: Medium | G15: Strong | H15: Very High | I15: 7–10 | J15: Every material finding exposes sources, uncertainty, missing evidence and alternative explanation.
... A28: Employee and manager benefit measurement | B28: Medium employer-centric | C28: Medium | D28: Strong team metrics | E28: Strong talent metrics | F28: Low | G28: Strong | H28: High | I28: 0,12 | J28: Product only succeeds when both task outcomes and employee development measurably improve.

Sheet Delivery Stages
A1: Delivery Stages
A2: 13 stages total. Stage 0 and Stage 1 are one Foundation & Validation workstream with separate approval gates; schedules are planning assumptions rather than delivery commitments.
A4: Stage # | B4: Stage | C4: Objective | D4: Duration weeks | E4: Indicative team size | F4: Dependencies | G4: Exit deliverables | H4: Lead role | I4: Current state | J4: Priority | K4: Risk | L4: Start date | M4: End date | N4: Effort PW
A5: 0 | B5: Foundation — charter, governance and legal boundary | C5: Define purpose, permitted/prohibited uses, lawful and ethical boundaries, employee rights, DPIA inputs, consultation, security principles, pilot protection and decision authority. | D5: 2 | E5: 8 | F5: None | G5: Product Charter v1; Purpose Policy Matrix; RACI; DPIA pack; threat model; pilot definition; Stage 0 gate. | H5: Executive Sponsor / Product / DPO | I5: Draft Complete — Gate Pending | J5: Critical | K5: High | L5: 46223 | M5: 46236 | N5: 16
A6: 1 | B6: Foundation — market validation and reference architecture | C6: Validate market/OSS landscape; decide build/buy/integrate/defer; define HumanOS reference architecture, ADRs, technical spikes, licences, costs and resource conditions. | D6: 2 | E6: 10 | F6: Stage 0 workstream runs in parallel; Stage 0 approval is required for implementation use | G6: Market/OSS research; Gap Matrix; Build/Buy decisions; Reference Architecture; ADRs; Stage 1 gate; Stage 2/3 prompts. | H6: CTO / Architecture / Product | I6: Draft Complete — Gate Pending | J6: Critical | K6: High | L6: 46223 | M6: 46236 | N6: 20
A7: 2 | B7: Role capability and task contract ontology | C7: Create domain-neutral Role Capability Contract, Task Execution Contract, evidence ontology, rubrics and implementation contracts, with software-development examples. | D7: 3 | E7: 7 | F7: Conditional Stage 0 and Stage 1 approval | G7: Schemas, rubrics, example roles/tasks, APIs/events, evaluator rules, backlog and Stage 2 gate. | H7: Product / Capability / AI / Domain Experts | I7: Specification Draft Complete — Gate Pending | J7: Critical | K7: High | L7: 46251 | M7: 46271 | N7: 21
A8: 3 | B8: Device agent foundation | C8: Build signed Windows/macOS agent skeleton, device identity, policy sync, visible session control, encrypted journal, update/rollback and spike framework. | D8: 5 | E8: 8 | F8: Conditional Stage 0 and Stage 1 approval | G8: Installable agent skeleton; registration; signed policy; session state machine; local journal; health/update; test and threat evidence. | H8: Desktop / Platform / Security | I8: Specification Draft Complete — Gate Pending | J8: Critical | K8: High | L8: 46272 | M8: 46306 | N8: 40
A9: 4 | B9: Telemetry ingestion and evidence storage | C9: Implement signed batch ingestion, schema governance, event bus, object evidence storage, audit linkage and replay APIs. | D9: 4 | E9: 7 | F9: Stage 3 foundation and approved event contracts | G9: Idempotent ingestion; schema registry; event topics; evidence/object storage; access and audit controls. | H9: Backend / Data / Platform | I9: Specification Draft Complete — Gate Pending | J9: Critical | K9: High | L9: 46307 | M9: 46334 | N9: 28
A10: 5 | B10: Universal capture MVP | C10: Capture approved application/window, visual-state, input metadata/text delta, idle, process and file evidence with local exclusions and redaction. | D10: 6 | E10: 9 | F10: Stages 3 and 4; DPIA and pilot control approval | G10: Correlated endpoint timeline; secure-field blocking; visual-state graph; edge redaction; performance and privacy tests. | H10: Desktop / Data / Security | I10: Specification Draft Complete — Gate Pending | J10: Critical | K10: High | L10: 46335 | M10: 46376 | N10: 54
A11: 6 | B11: Development semantics and AI-agent adapters | C11: Add browser, terminal, Git, tests/builds, Codex, Claude Code, IDE and toolchain adapters. | D11: 6 | E11: 9 | F11: Stage 5 | G11: Normalised agent/tool events; terminal/process semantics; Git/test/build evidence; adapter SDK. | H11: Integrations / AI / Developer Platform | I11: Specification Draft Complete — Gate Pending | J11: High | K11: High | L11: 46377 | M11: 46418 | N11: 54
A12: 7 | B12: Provenance and Task Assurance Engine | C12: Build work episodes, task alignment, human/AI/automation causal graph, acceptance-criteria and quality evaluation. | D12: 7 | E12: 10 | F12: Stages 2 and 6 | G12: Evidence/provenance graph; task assessments; criterion state; confidence calibration; blocker detection; human review. | H12: AI / Backend / Product | I12: Specification Draft Complete — Gate Pending | J12: Critical | K12: High | L12: 46419 | M12: 46467 | N12: 70
A13: 8 | B13: Capability Graph and baseline assessment | C13: Map role requirements and employee claims to repeated, context-qualified capability evidence and role readiness. | D13: 5 | E13: 8 | F13: Stages 2 and 7 | G13: Capability service; baseline assessment; claim-evidence discrepancy workflow; fairness/evidence tests. | H13: Capability / HR / AI / Backend | I13: Specification Draft Complete — Gate Pending | J13: High | K13: High | L13: 46468 | M13: 46502 | N13: 40
A14: 9 | B14: Growth Coach and learning loop | C14: Provide controlled observe/nudge/assist/teach/escalate interventions, training plans and effectiveness measurement. | D14: 5 | E14: 8 | F14: Stages 7 and 8 | G14: Coaching orchestration; learning plans; mentor escalation; intervention safety; applied-learning evidence. | H14: AI / L&D / Product | I14: Specification Draft Complete — Gate Pending | J14: High | K14: Medium | L14: 46503 | M14: 46537 | N14: 40
A15: 10 | B15: Employee and manager experiences | C15: Deliver employee timeline/corrections/capability view and manager exception-led task/capability reports. | D15: 5 | E15: 9 | F15: Stages 7–9 and governance workflow | G15: Employee portal; dispute/review workflow; manager task assurance; access controls; usability evidence. | H15: Product / Frontend / Backend / Governance | I15: Specification Draft Complete — Gate Pending | J15: High | K15: High | L15: 46538 | M15: 46572 | N15: 45
A16: 11 | B16: Skill Forge and governed self-improvement | C16: Create observation-to-skill/evaluator improvement with evaluation, approval, canary, promotion and rollback. | D16: 6 | E16: 8 | F16: Stages 9 and 10 | G16: Skill registry; proposal/evaluation pipeline; confidentiality controls; approval/canary/rollback. | H16: AI Platform / Governance | I16: Specification Draft Complete — Gate Pending | J16: High | K16: High | L16: 46573 | M16: 46614 | N16: 48
A17: 12 | B17: Security hardening, internal pilot and rollout decision | C17: Complete penetration/privacy/performance/evaluation testing, controlled pilot, evidence review, cost analysis and proceed/modify/restrict/stop decision. | D17: 8 | E17: 12 | F17: Stages 0–11, approved Architecture Amendment A-01 and all pilot approvals | G17: Pilot report; legal/DPO/security sign-off; employee/manager evidence; cost and launch-readiness decision. | H17: Executive Sponsor / CTO / DPO / CISO / Product | I17: Final Stage 12 Plan Complete — Hardening and Pilot Not Executed | J17: Critical | K17: High | L17: 46615 | M17: 46670 | N17: 96
A18: A-01 | B18: Architecture amendment — AI execution and orchestration separation | C18: Separate Work Intelligence from provider/model execution; integrate existing HumanOS AI Orchestrator; define compatible standalone/endpoint modes, qualification and routing. | D18: 3 | E18: 10 | F18: Stages 0–11 specification baseline; existing AI orchestrator capability inventory | G18: Baseline v1.1; shared AI contracts; orchestrator/standalone/endpoint designs; qualification/routing/fallback; revised Stage 12 prompt; A-01 gate. | H18: CTO / Enterprise Architecture / AI Platform / Work Intelligence | I18: Specification Complete — Formal Approval and Implementation Pending | J18: Critical | K18: High | L18: =M18-D18*7+1 -> 46594 | M18: =L17-1 -> 46614 | N18: 30

Sheet Microservices Map
A1: Microservices and Deployment Map
A2: Initial physical deployment plan. Logical bounded contexts can be separated later, but a new deployable requires a demonstrated security, scale, availability, ownership or transactional boundary.
A4: Deployable / component | B4: Includes bounded contexts | C4: Primary responsibility | D4: Primary runtime | E4: Primary stores | F4: Consumes / integrates | G4: Publishes / exposes | H4: HumanOS foundation reuse | I4: Initial stage | J4: Future split trigger | K4: Owner / note
A5: Endpoint Device Agent | B5: Native core; Windows bridge; macOS bridge; local policy; session control; encrypted journal; uploader; health/update; adapter SDK. | C5: Visible, policy-controlled endpoint evidence collection, local minimisation/redaction, offline durability and signed event batching. | D5: Rust shared core + Swift + Windows native bridge + TypeScript browser extension | E5: Encrypted SQLite/SQLCipher-style journal and content-addressed local cache | F5: Device policy, HumanOS session/task context, OS/application/agent adapters | G5: Signed event batches, device health, policy status, telemetry gaps | H5: Device identity, policy, secrets, audit, notification | I5: 3–6 | J5: OS-specific components may become separate packages, not necessarily cloud services. | K5: Desktop Platform
A6: Deployable 1 — Device Control & Policy Gateway | B6: Device registry; certificate lifecycle; policy distribution; session command/control; update rollout metadata; agent health. | C6: Cloud control plane for managed devices and capture policy. | D6: Java + Spring Boot | E6: PostgreSQL | F6: IAM, organisation, device attestation/MDM, policy service, secrets/KMS | G6: Registration/session/policy/update APIs and device events | H6: Identity, organisation, policy, secrets, audit, notification, API gateway | I6: 3–4 | J6: Split update service or fleet health if endpoint scale/ownership demands it. | K6: Platform / Security
A7: Deployable 2 — Telemetry Ingestion & Schema | B7: Batch gateway; signature validation; idempotency; tenant partitioning; schema registry integration; quotas; reject/diagnostics. | C7: Receive signed endpoint/adapter batches and publish normalised, replayable events. | D7: Java + Spring Boot + Spring Kafka | E7: Kafka-compatible bus + PostgreSQL ingestion metadata | F7: Device certificates, tenant/IAM, schema registry, event bus | G7: Normalised event topics, batch receipts, telemetry gap and rejection events | H7: IAM, event infrastructure, audit, API gateway | I7: 4 | J7: Scale ingress independently by region or workload when measured. | K7: Backend / Data Platform
A8: Deployable 3 — Evidence & Timeline | B8: Activity events; visual-state metadata; artefact references; relational provenance edges; retention; timeline/replay; evidence access. | C8: System of record for work evidence metadata and evidence-linked timelines. | D8: Java + Spring Boot | E8: PostgreSQL + object storage; search indexes as needed | F8: Normalised events, task/project context, file/Git/test/agent events, policy decisions | G8: Evidence/timeline APIs; evidence.linked and provenance.updated events | H8: Object/file service, policy, audit, IAM, tenant | I8: 4–7 | J8: Split visual/object indexing if retention/security/throughput becomes independent. | K8: Data / Evidence
A9: Deployable 4A — Task Assurance Domain | B9: Task contract state; acceptance criteria; deterministic validators; assessment workflow; blocker and task-alignment state. | C9: Own durable task-assurance lifecycle and orchestrate evaluators and human review. | D9: Java + Spring Boot | E9: PostgreSQL | F9: HumanOS tasks/projects/workflow, evidence, build/test/CI, reviewer decisions | G9: Task assessment/criterion/blocker APIs and events | H9: Task/project service, workflow, policy, audit, notification | I9: 2,7 | J9: Separate task-contract compiler or validator workers only after independent scale/ownership. | K9: Product / Backend
A10: Deployable 4B — Task & Activity Evaluators | B10: Episode segmentation; task alignment; visual/text interpretation; quality reasoning; confidence calibration; evaluation harness. | C10: Return versioned, evidence-linked AI findings without owning final employment or task state. | D10: Python + FastAPI/worker runtime | E10: Evaluation/model artefact store + approved vector/search index | F10: Evidence references and minimised approved content through Model Gateway | G10: Evaluator findings, confidence, missing evidence and model/skill metadata | H10: Model Gateway, policy, audit, secrets, observability | I10: 7 | J10: Separate model-specific worker pools based on compute/security class. | K10: AI / Evaluation
A11: Deployable 5A — Capability & Learning Domain | B11: Role capability contracts; claims; evidence state; role readiness; learning plans; intervention workflow; employee capability view. | C11: Own transparent capability and learning lifecycle across HumanOS verticals. | D11: Java + Spring Boot | E11: PostgreSQL | F11: Organisation/roles, task assessments, baseline assessments, training outcomes, review decisions | G11: Capability evidence/state, gap, learning and role-readiness APIs/events | H11: Organisation/role, workflow, HR integrations, policy, audit, notification | I11: 2,8–9 | J11: Split learning marketplace/content integration if volume and ownership justify. | K11: Capability Product / L&D
A12: Deployable 5B — Capability Scoring & Coaching AI | B12: Evidence weighting; confidence/recency/consistency; gap classification; coaching generation; training recommendations; effectiveness evaluation. | C12: Provide explainable recommendations to the durable Capability & Learning domain. | D12: Python + FastAPI/worker runtime | E12: Evaluation store + approved skill/content index | F12: Qualified capability evidence, task context, employee request and approved learning content | G12: Scoring/coaching recommendations with explanations and version metadata | H12: Model Gateway, policy, audit, workflow | I12: 8–9 | J12: Separate coaching latency path from batch capability scoring if required. | K12: AI / L&D
A13: Deployable 6 — AI Adapter & Memory Hub | B13: Codex/Claude/IDE agent adapters; provider-normalised lifecycle; prompt/tool observation; approved session memory; model/evaluation routing extensions. | C13: Connect AI work surfaces to HumanOS evidence and provide provider-neutral agent provenance. | D13: Python adapters + Java API/orchestration; extend existing HumanOS Model Gateway | E13: PostgreSQL metadata + approved search/vector index | F13: Official agent hooks, MCP/tool events, Model Gateway, evidence/task context | G13: Normalised agent events, memory/search APIs and AI audit | H13: Model Gateway, secrets, policy, audit, event bus | I13: 6,11 | J13: Split provider adapters or memory service when scale/security/ownership demands it. | K13: AI Platform / Integrations
A14: Deployable 7 — Governance & Human Review | B14: Employee evidence access; corrections; disputes; manager raw-evidence requests; human review; policy/decision reasons; consequential-decision safeguards. | C14: Operationalise employee rights and meaningful human review before assessments are used. | D14: Java + Spring Boot | E14: PostgreSQL + immutable audit references | F14: Assessment/dispute/access requests, identity/organisation, workflow and policy | G14: Review/correction/access decision APIs and events | H14: Workflow Runtime, IAM, policy, audit, notification | I14: 0,7–10 | J14: Split access-control admin from review case management only if security ownership differs. | K14: Governance / HR / DPO
A15: Deployable 8 — Reporting & Analytics | B15: Employee timeline read model; manager task assurance; capability views; pilot KPI; team/process and executive reporting. | C15: Deliver role-appropriate, exception-led views without making raw evidence the default experience. | D15: Java APIs + frontend/BI; Python/SQL analytics where justified | E15: PostgreSQL read models; warehouse/lakehouse later | F15: Task, capability, review, workflow and aggregated evidence events | G15: Reports, dashboards, exports and analytics APIs | H15: IAM, organisation, audit, notification, existing analytics platform | I15: 10 | J15: Separate analytics pipeline/warehouse after data-volume and governance proof. | K15: Product Analytics
... A21: Shared HumanOS — Event, API & Observability Platform | B21: Kafka-compatible event bus; schema registry; API gateway; service mesh/mTLS; OpenTelemetry; deployment/feature flags. | C21: Provide cross-service contracts, security, operations and regional deployment. | D21: Existing HumanOS platform | E21: Kafka/schema/telemetry/platform stores | F21: All services and agents | G21: Events, APIs, traces/metrics/logs and deployments | H21: Authoritative foundation | I21: 1+ | J21: Operational telemetry must not become the raw employee-evidence store. | K21: Platform / SRE
A25: Architecture Amendment A-01 — Deployment Map Extensions
A26: Deployable / component | B26: Includes bounded contexts | C26: Primary responsibility | D26: Primary runtime | E26: Primary stores | F26: Consumes / integrates | G26: Publishes / exposes | H26: HumanOS foundation reuse | I26: Initial stage | J26: Future split trigger | K26: Owner / note
A27: Shared library — Work Intelligence AI Client | B27: AI Execution Port; task/effort contract; deterministic/no-AI fallback. | C27: Keep Work Intelligence provider-neutral and submit purpose-oriented AI jobs. | D27: Java library/generated client | E27: No secrets; request/result refs | F27: Task Assurance, Capability, Coaching, Research | G27: AI job calls and canonical error handling | H27: Policy, audit, workflow | I27: A-01 | J27: Version/contract compatibility requires independent package release. | K27: Work Intelligence / API Architecture
A28: Existing deployable — HumanOS AI Orchestrator | B28: Provider connectors; credentials; model registry; qualification; routing; fallback; cost/health/drift. | C28: Preferred central AI execution implementation across HumanOS modules. | D28: Existing AI platform stack | E28: PostgreSQL/config/eval/object stores | F28: Secrets/KMS, providers, cloud/self-hosted endpoints, Task Profiles | G28: AIJobResult, route/qualification/drift events | H28: Secrets, Model Gateway, policy, audit, event bus | I28: A-01,12 | J28: Split high-compute evaluators only for scale/security class. | K28: AI Platform / Preferred
A29: Optional deployable — Standalone AI Router | B29: Compatible connectors; scoped registry; imported qualification; routing/fallback/audit. | C29: Isolated/customer/resilience implementation of the same AI contract. | D29: Java/Spring or approved lightweight stack | E29: Scoped PostgreSQL/config/cache | F29: Shared contracts, credentials, endpoint broker, provider endpoints | G29: Canonical job results and health | H29: Policy, secrets, audit, events | I29: A-01,12 | J29: Deploy only where central orchestrator cannot satisfy boundary. | K29: AI Platform / Optional
A30: Endpoint module — AI Runtime Broker | B30: CLI/local runtime discovery; auth health; sandboxed execution; resource controls; user messaging. | C30: Execute visible endpoint subscription CLI/local-model jobs without exposing credentials. | D30: Rust + native process/IPC adapters | E30: Encrypted local inventory/temporary refs | F30: Codex/Claude/Kimi/Antigravity/Qwen/Ollama and local policy | G30: Canonical job result, health and action-required events | H30: Device identity, policy, notification, audit | I30: A-01,12 | J30: May be independently packaged if update/security ownership requires. | K30: Desktop AI Platform
A31: Shared capability — Model Qualification | B31: Task/effort registry; datasets; graders; profiles; drift/regression. | C31: Qualify exact execution configurations and publish signed portable profiles. | D31: Java + Python eval workers | E31: Evaluation/object store + registry | F31: Provider/model/runtime/CLI configurations and Skill Forge packages | G31: Qualification profiles and alerts | H31: Workflow, audit, object, Model Gateway | I31: A-01,12 | J31: Independent worker pools by modality/security/compute. | K31: AI Evaluation / Governance

Sheet MVP Backlog
A1: MVP Backlog
A2: Initial epics and features for the controlled internal pilot.
A4: Epic ID | B4: Epic | C4: Feature / user story | D4: Stage | E4: Owner | F4: Priority | G4: Status | H4: Effort pts | I4: Acceptance criteria | J4: Dependencies | K4: Notes
A5: E01 | B5: Work session control | C5: Employee can start/pause/stop a monitored work session against a HumanOS task. | D5: 3 | E5: Desktop/Backend | F5: Critical | G5: Not Started | H5: 8 | I5: Session event exists; visible status; offline buffering; task ID linked. | J5: Device Agent Gateway | K5: No hidden mode.
A6: E02 | B6: Policy sync | C6: Agent receives tenant/jurisdiction/capture policy before recording. | D6: 3 | E6: Platform/Security | F6: Critical | G6: Not Started | H6: 8 | I6: Policy signature verified; excluded apps/domains applied; audit emitted. | J6: Policy Service | K6: Policy version visible.
A7: E03 | B7: App/window telemetry | C7: Capture foreground app, process, window title and transitions. | D7: 5 | E7: Desktop | F7: Critical | G7: Not Started | H7: 5 | I7: 99% foreground app transition capture in pilot. | J7: Agent foundation
A8: E04 | B8: Click + visual state | C8: Capture mouse click with pre/post visual states and changed region. | D8: 5 | E8: Desktop/AI | F8: Critical | G8: Not Started | H8: 13 | I8: 98% click-to-state correlation in supported pilot apps. | J8: Visual Evidence Store
A9: E05 | B9: Text-state capture | C9: Reconcile physical input, text deltas and resulting artefact changes in approved controls. | D9: 5 | E9: Desktop/Data | F9: Critical | G9: Not Started | H9: 21 | I9: 95% reconstruction in supported controls; zero secure-field leakage. | J9: Policy / UI accessibility | K9: Avoid raw keylogger-only logic.
A10: E06 | B10: File/process telemetry | C10: Capture process tree, file create/modify/delete and build/test process markers. | D10: 5 | E10: Desktop/Data | F10: High | G10: Not Started | H10: 13 | I10: Event causal chain links process -> file/test output. | J10: ETW/macOS process bridge
A11: E07 | B11: Browser adapter | C11: Capture active tab, title, approved URL/domain, navigation and visible page event. | D11: 6 | E11: Integrations | F11: High | G11: Not Started | H11: 8 | I11: Chrome/Edge MV3 extension sends normalized events. | J11: Native messaging
A12: E08 | B12: Terminal adapter | C12: Capture command, cwd, exit code, stdout/stderr summary and process duration. | D12: 6 | E12: Integrations | F12: High | G12: Not Started | H12: 13 | I12: Command event links to resulting processes and files. | J12: Shell/PTTY hooks
A13: E09 | B13: Git adapter | C13: Capture branch, diff summary, commit, PR, changed files and reviewer state. | D13: 6 | E13: Integrations | F13: High | G13: Not Started | H13: 8 | I13: Git diff/commit events linked to task and actor. | J13: GitHub/GitLab connectors
A14: E10 | B14: Codex adapter | C14: Capture Codex prompt/tool/permission/stop lifecycle via hooks. | D14: 6 | E14: AI Integrations | F14: Critical | G14: Not Started | H14: 8 | I14: Agent events mapped to OTel-style spans and provenance graph. | J14: Codex hooks
A15: E11 | B15: Claude Code adapter | C15: Capture Claude Code usage through hooks/OTel/MCP where available. | D15: 6 | E15: AI Integrations | F15: High | G15: Not Started | H15: 8 | I15: Prompt/tool/file/command events normalized. | J15: Claude Code config
A16: E12 | B16: Episode segmentation | C16: Group raw events into meaningful 30-180 second work episodes. | D16: 7 | E16: AI/Data | F16: Critical | G16: Not Started | H16: 21 | I16: Episodes align with human review >=90% in pilot sample. | J16: Evidence graph
A17: E13 | B17: Task alignment classifier | C17: Classify episodes as on-task, supporting, blocked, automated-wait, idle, unrelated. | D17: 7 | E17: AI | F17: Critical | G17: Not Started | H17: 21 | I17: False idle below 5%; confidence calibrated. | J17: Task contracts
A18: E14 | B18: Acceptance criteria validator | C18: Determine task completion evidence and missing verification. | D18: 7 | E18: AI/Product | F18: Critical | G18: Not Started | H18: 21 | I18: Every criterion has evidence, status and confidence. | J18: Task contract
A19: E15 | B19: Capability graph MVP | C19: Create role capability profile and update capability evidence after assessed tasks. | D19: 8 | E19: AI/Backend | F19: High | G19: Not Started | H19: 13 | I19: Capability level, confidence, recency and evidence visible. | J19: Role ontology
A20: E16 | B20: Growth coach MVP | C20: Generate non-disruptive guidance when task risk or capability gap is detected. | D20: 9 | E20: AI/L&D | F20: High | G20: Not Started | H20: 13 | I20: Nudge/assist/teach messages audited; employee can dismiss/correct. | J20: Task intelligence
A21: E17 | B21: Employee portal | C21: Employee can see timeline, report, capability profile and dispute findings. | D21: 10 | E21: Frontend | F21: Critical | G21: Not Started | H21: 13 | I21: Dispute creates review workflow; employee evidence visible. | J21: Reporting/Governance
... A24: E20 | B24: Pilot validation | C24: Run internal pilot and measure capture accuracy, task alignment, worker trust and manager value. | D24: 12 | E24: Leadership/QA | F24: Critical | G24: Not Started | H24: 21 | I24: Pilot report with acceptance metrics and rollout decision. | J24: All MVP epics

Sheet Event Data Model
A1: Event & Data Model
A2: Core evidence graph, events, entities and provenance relationships.
A4: Model area | B4: Entity/Event | C4: Purpose | D4: Key fields | E4: Producer | F4: Consumer | G4: MVP | H4: Notes | I4: Source/ref
A5: Entity | B5: WorkSession | C5: Tracks a monitored work period and task linkage. | D5: session_id, person_id, device_id, task_id, start/end, policy_version | E5: Device Agent Gateway | F5: Task Intelligence, Reporting | G5: Yes | H5: Supports pause/private/excluded segments.
A6: Entity | B6: TaskExecutionContract | C6: Structured task expectations and acceptance criteria. | D6: objective, criteria, evidence_required, tools, risks, reviewer | E6: Task Intelligence | F6: Task Assurance, Coach | G6: Yes | H6: Compiled from HumanOS task.
A7: Entity | B7: RoleCapabilityContract | C7: Structured role/job description capability requirements. | D7: role, level, capabilities, evidence rubrics, autonomy | E7: Role & Capability | F7: Capability Graph | G7: Yes | H7: Job description becomes measurable contract.
A8: Event | B8: activity.application.changed | C8: Foreground app/window/process transition. | D8: app, pid, window_title, timestamp, confidence | E8: Desktop Agent | F8: Evidence Service | G8: Yes | H8: Universal capture stream.
A9: Event | B9: activity.input.observed | C9: Physical mouse/keyboard input metadata. | D9: input_type, key/button, coordinate, injected_flag, secure_field | E9: Desktop Agent | F9: Evidence Service | G9: Yes | H9: Text stored separately and controlled. | I9: Microsoft SetWindowsHookEx
A10: Event | B10: activity.visual.changed | C10: Visual state changed due to click/app/action. | D10: before_state, after_state, changed_region, screenshot_hash | E10: Desktop Agent | F10: Evidence Service | G10: Yes | H10: Event-driven capture, not brute-force video.
A11: Event | B11: activity.text.changed | C11: Resulting text delta in an approved control/editor. | D11: inserted_ref, deleted_ref, source_control, privacy_class | E11: Desktop Agent/IDE Adapter | F11: Evidence, Task Intelligence | G11: Yes | H11: Authoritative text-state > raw keys.
A12: Event | B12: agent.prompt.submitted | C12: Prompt sent to Codex/Claude/Cursor/etc. | D12: agent, prompt_ref, task_id, turn_id | E12: AI Agent Adapter | F12: Provenance, Coach | G12: Yes | H12: Use official hooks where possible. | I12: Codex hooks
A13: Event | B13: agent.tool.completed | C13: Agent tool command or file operation completed. | D13: tool, input_ref, output_ref, exit_code, files_touched | E13: AI Agent Adapter | F13: Provenance | G13: Yes | H13: Causal parent is prompt or prior tool call. | I13: OpenTelemetry GenAI
A14: Event | B14: process.completed | C14: System command/build/test process ended. | D14: command_ref, cwd, exit_code, duration, stdout_ref | E14: Terminal/OS Adapter | F14: Task Assurance | G14: Yes | H14: Distinguish automated wait from idle.
A15: Event | B15: task.criterion.verified | C15: Task criterion satisfied or failed with evidence. | D15: criterion_id, status, evidence_refs, confidence | E15: Task Intelligence | F15: Reporting/Capability | G15: Yes | H15: Outcome-driven assessment.
A16: Event | B16: capability.evidence.recorded | C16: Capability evidence gained from a task episode. | D16: capability_id, level_signal, confidence, evidence_refs | E16: Role & Capability | F16: Learning/Reporting | G16: Yes | H16: Repeated evidence updates profile.
A17: Event | B17: skill.observation.created | C17: Candidate improvement to HumanOS skill/plugin/evaluator. | D17: issue, improvement, principle, evidence_refs, confidentiality | E17: Skill Forge | F17: Skill Review | G17: Later | H17: Human approval before activation.

Sheet AI Capability System
A1: AI Capability System
A2: How Nessovo verifies capability, improves employees, and improves HumanOS itself.
A4: Level | B4: Name | C4: Meaning | D4: Evidence examples | E4: Manager interpretation | F4: Employee experience
A5: 0 | B5: Unverified | C5: Claim exists but no reliable evidence yet. | D5: Onboarding claim, CV, self-assessment. | E5: Do not assume capability; assign baseline tasks. | F5: Skill locked or greyed out.
A6: 1 | B6: Learning | C6: Requires direct instruction and close guidance. | D6: Fails routine tasks without support; training in progress. | E6: Needs guided work and mentor review. | F6: Starter quests and basic lessons.
A7: 2 | B7: Assisted | C7: Can complete routine work with support. | D7: Completes tasks when guided; recurring review required. | E7: Suitable for scoped tasks. | F7: Progress quests and coaching.
A8: 3 | B8: Independent | C8: Reliably completes standard work independently. | D8: Multiple successful tasks with appropriate verification. | E8: Meets normal role requirement. | F8: Core skill unlocked.
A9: 4 | B9: Advanced | C9: Handles complex/non-routine work and supports others. | D9: Solves unfamiliar variants; mentors peers; improves playbooks. | E9: Can own complex workstreams. | F9: Advanced challenges and mentor badges.
A10: 5 | B10: Mastery | C10: Defines standards, solves novel problems and coaches others. | D10: Creates reusable methods; reviews designs; leads standards. | E10: Can define organisational practice. | F10: Mastery status and skill authoring.
A13: Loop | B13: Input | C13: AI action | D13: Human control | E13: Output
A14: Employee learning loop | B14: Task evidence, errors, coaching response | C14: Detect gap and recommend training/practice | D14: Employee can challenge; manager/mentor reviews | E14: Capability evidence and learning plan
A15: Task assurance loop | B15: Task contract, activity episodes, artefacts | C15: Assess task alignment, progress, quality and completion | D15: Lead/reviewer decides status | E15: Evidence-backed task report
A16: Organisational learning loop | B16: Repeated successful work patterns | C16: Propose playbooks/templates/workflows | D16: Domain expert approves | E16: HumanOS workflow / standard method
A17: Skill Forge loop | B17: User correction, evaluator failure, new research | C17: Propose skill/plugin/evaluator update | D17: Skill reviewer, tests, canary, rollback | E17: Versioned HumanOS skill
A20: Evaluator | B20: Purpose | C20: Runtime | D20: Inputs | E20: Outputs | F20: MVP
A21: Task alignment classifier | B21: Classify episode relative to assigned task. | C21: Python | D21: Episode, task contract, app context, artefacts | E21: classification + confidence + evidence refs | F21: Yes
A22: Provenance classifier | B22: Classify human/AI/automation/system actor. | C22: Python + rules | D22: Input events, agent hooks, process tree, file deltas | E22: actor + confidence + causal edge | F22: Yes
A23: Acceptance criteria verifier | B23: Determine criterion status and missing evidence. | C23: Python + deterministic validators | D23: Task contract, artefacts, tests, screenshots, reports | E23: met/partial/missing + evidence | F23: Yes
A24: Capability updater | B24: Update capability confidence and level from evidence. | C24: Python scoring + Java persistence | D24: Task assessment, difficulty, independence, guidance | E24: capability signal + level update proposal | F24: Yes
A25: Coaching selector | B25: Choose whether/how to intervene. | C25: Python | D25: Risk, confidence, history, user preferences | E25: nudge/assist/teach/escalate/observe | F25: Yes
A26: Skill improvement evaluator | B26: Test proposed skill/plugin changes. | C26: Python | D26: Observation, skill diff, test corpus, policy constraints | E26: pass/fail/regression/risk report | F26: Later

Sheet Governance
A1: Governance and Compliance Control Baseline
A2: Minimum Stage 0 controls. This workbook defines the requirements; legal, DPO, security, HR and worker-consultation approvals remain necessary before an employee pilot.
A4: Control ID | B4: Control area | C4: Mandatory requirement | D4: Implementation direction | E4: Accountable owner | F4: Pilot blocking | G4: Required evidence | H4: Control status | I4: Primary risk reduced | J4: Source / note
A5: GOV-001 | B5: Purpose and necessity | C5: Every collected or derived data category has a specific approved purpose, necessity analysis and less-intrusive alternative assessment. | D5: Purpose Policy Matrix, policy identifiers in events, periodic DPO review. | E5: DPO / Product | F5: Yes | G5: Approved matrix and DPIA. | H5: Draft Ready | I5: Excessive or repurposed surveillance. | J5: ICO monitoring guidance.
A6: GOV-002 | B6: Transparency | C6: Workers understand what is captured, when, why, who can see it, retention, automated analysis and rights. | D6: Clear privacy notice, monitoring policy, onboarding, visible endpoint status and policy version. | E6: DPO / HR / Legal | F6: Yes | G6: Approved notice/policy and acknowledgement record. | H6: Draft Ready | I6: Unfair/opaque processing and trust failure. | J6: GOV.UK / ICO.
A7: GOV-003 | B7: Worker consultation | C7: Affected workers or representatives are consulted before design is frozen and before material policy changes. | D7: Consultation plan, facilitated sessions, issue log, Nessovo response and change record. | E7: HR / DPO | F7: Yes | G7: Consultation record. | H7: Not Started | I7: Lack of worker voice and undiscovered harms. | J7: ICO and UK consultation direction.
A8: GOV-004 | B8: DPIA | C8: High-risk monitoring and employment AI receive a completed DPIA and recorded DPO advice before pilot. | D8: Governance workflow, risk register, mitigation owners, residual-risk acceptance and review date. | E8: DPO | F8: Yes | G8: Completed DPIA and advice. | H8: Not Started | I8: Regulatory and employee harm. | J8: ICO.
A9: GOV-005 | B9: Jurisdiction review | C9: UK and Pakistan/Lahore deployments have separate legal and employment assessments; EU customer deployment receives AI Act/GDPR analysis. | D9: Jurisdiction policy packs, data-flow maps, contractual safeguards and deployment flags. | E9: Legal / DPO | F9: Yes | G9: Legal memoranda and approved policy packs. | H9: Owner Input | I9: Cross-border and local-law non-compliance. | J9: Local counsel required.
A10: GOV-006 | B10: No covert general monitoring | C10: The product has no routine hidden mode; any exceptional investigation is separate, specific, time-limited and legally authorised. | D10: Visible status, signed policy, restricted investigation workflow outside normal product operation. | E10: Legal / DPO / CISO | F10: Yes | G10: Product test and policy approval. | H10: Draft Ready | I10: Unlawful covert surveillance. | J10: GOV.UK.
A11: GOV-007 | B11: Secure-field and secret blocking | C11: Passwords, authentication codes, known secure fields and detected secrets are suppressed before durable storage or upload. | D11: OS secure-control detection, local secret scanning/redaction, exclusion policy, zero-retention suppression event. | E11: CISO / Desktop | F11: Yes | G11: Adversarial leakage test with zero known-secret retention. | H11: Draft Ready | I11: Credential/IP/data breach. | J11: Privacy engineering requirement.
A12: GOV-008 | B12: Application/domain/hour exclusions | C12: Personal/sensitive apps, domains, monitors and out-of-policy hours cannot be captured. | D12: Signed local policy, employee-visible exclusions, fail-safe behaviour and audit. | E12: DPO / HR / Security | F12: Yes | G12: Policy tests and endpoint audit. | H12: Draft Ready | I12: Private-life and special-category exposure. | J12: Purpose Policy Matrix.
A13: GOV-009 | B13: Edge minimisation | C13: Deduplication, event-driven capture, changed regions, redaction and aggregation occur locally wherever feasible. | D13: Native agent pipeline and privacy budget. | E13: CISO / DPO / Desktop | F13: Yes | G13: Data-flow and benchmark evidence. | H13: Draft Ready | I13: Data concentration and cost.
A14: GOV-010 | B14: Raw evidence access | C14: Raw screenshots/text/keystrokes are not default manager content and require role, purpose, task, time and audit authorisation. | D14: Summary-first UX, purpose codes, ABAC/policy decisions, JIT access and immutable access log. | E14: Security / DPO / HR | F14: Yes | G14: Access-control tests and audit review. | H14: Draft Ready | I14: Manager/insider misuse.
A15: GOV-011 | B15: Employee access and correction | C15: Employees can view material evidence and assessments, correct task attribution/context and add explanations. | D15: Employee portal and correction workflow preserving original/corrected lineage. | E15: Product / DPO | F15: Yes | G15: UX test and correction audit. | H15: Draft Ready | I15: False or incomplete conclusions. | J15: ICO accuracy/challenge.
A16: GOV-012 | B16: Dispute and human review | C16: Employees can request review; qualified reviewers consider context and can reject AI findings. | D16: Workflow SLA, reviewer qualifications, evidence package, reasoned decision and override logging. | E16: HR / Legal / DPO | F16: Yes | G16: End-to-end review test. | H16: Draft Ready | I16: Rubber-stamped automated decisions. | J16: ICO human review.
A17: GOV-013 | B17: Consequential decisions | C17: No solely automated dismissal, discipline, pay, promotion, probation or equivalent decision. | D17: Policy and workflow block final decision state without authorised human decision and supporting evidence. | E17: HR / Legal | F17: Yes | G17: Decision audit and policy test. | H17: Draft Ready | I17: Employment harm and automated-decision breach.
A18: GOV-014 | B18: Evidence hierarchy | C18: Authoritative system outcomes and artefacts outrank tool, OS, accessibility, visual and AI inference evidence. | D18: Typed evidence classes and evaluator rules. | E18: Product / Data / AI | F18: Yes | G18: Evaluation tests and report explainability. | H18: Draft Ready | I18: Screenshot/AI narrative overriding facts.
A19: GOV-015 | B19: Confidence and uncertainty | C19: Material AI findings include confidence, evidence, missing evidence, alternative explanation, model/skill version and review status. | D19: Evaluator output schema and report UI. | E19: AI Governance | F19: Yes | G19: Calibration/evidence-grounding test. | H19: Draft Ready | I19: Overconfident false allegation. | J19: NIST AI RMF.
A20: GOV-016 | B20: Prohibited inference | C20: No emotion, personality, honesty, protected-trait, health or mental-state inference from computer activity. | D20: Model-policy deny list, prompt/evaluator tests and review. | E20: AI Governance / DPO | F20: Yes | G20: Prohibited-output red-team results. | H20: Draft Ready | I20: Discriminatory or unlawful inference. | J20: EU employment AI risk context.
A21: GOV-017 | B21: Outcome over activity | C21: Clicks, keys, code volume and hours are not used as standalone productivity or capability scores. | D21: Metric-policy rules and report tests. | E21: Product / HR | F21: Yes | G21: KPI/report review. | H21: Draft Ready | I21: Gaming and unfair management.
A22: GOV-018 | B22: Capability evidence | C22: Capability levels require repeated, context-qualified evidence, independence and quality; one task cannot establish dishonesty or permanent incapability. | D22: Stage 2 ontology, evidence thresholds, contradiction/recency and human review. | E22: Capability Lead / HR | F22: Yes before capability pilot | G22: Ontology/evaluation/fairness tests. | H22: Draft Ready | I22: Career harm and deceptive labels.
A23: GOV-019 | B23: Training use | C23: Detected gaps first support explanation, coaching, training and reassessment; training completion alone does not increase capability. | D23: Learning workflow and applied-evidence rule. | E23: HR / L&D / Product | F23: No for capture pilot; yes for capability use | G23: Learning effectiveness design. | H23: Draft Ready | I23: Punitive or performative learning.
A24: GOV-020 | B24: Retention and deletion | C24: Raw evidence has short purpose-based retention; derived records have justified retention, deletion, export and legal-hold controls. | D24: Per-class retention policy, object lifecycle, deletion verification and employee request workflow. | E24: DPO / Data Governance | F24: Yes | G24: Approved schedule and deletion tests. | H24: Owner Input | I24: Data concentration and over-retention.
A25: GOV-021 | B25: Model/provider governance | C25: Employee evidence only uses approved Model Gateway routes, contracts and regional/private processing appropriate to its classification. | D25: Provider allowlist, no-training/retention terms, egress controls and model audit. | E25: AI Platform / CISO / Legal | F25: Yes | G25: Provider contracts and egress tests. | H25: Owner Input | I25: Third-party retention/training/exposure.
A26: GOV-022 | B26: Prompt injection and tool safety | C26: Observed content is untrusted data; evaluators and coaches cannot expand privileges or follow embedded instructions. | D26: Prompt isolation, tool restrictions, retrieval allowlists, output validation and adversarial tests. | E26: AI Security | F26: Yes before AI pilot | G26: Indirect-injection benchmark. | H26: Draft Ready | I26: Model manipulation and data exfiltration.
A27: GOV-023 | B27: Auditability | C27: Evidence access, policy decisions, AI findings, human reviews, corrections and skill changes are immutably auditable. | D27: Existing HumanOS audit extension and correlation identifiers. | E27: CISO / Audit | F27: Yes | G27: Audit coverage test. | H27: Draft Ready | I27: Undetectable misuse or unaccountable decisions.
A28: GOV-024 | B28: Skill/evaluator governance | C28: System improvements are proposals until evaluation, expert/security review, canary and rollback; confidential data is not leaked into reusable skills. | D28: Skill Forge lifecycle, signed versions, eval suites, internal/open classification and deployment gates. | E28: AI Platform / Governance | F28: Yes before Stage 11 production | G28: Regression and confidentiality tests. | H28: Draft Ready | I28: Unsafe self-modification and IP leakage. | J28: Task Observer/Claude-Mem patterns.
A29: GOV-025 | B29: Pilot participant protection | C29: Pilot outputs are developmental/evaluative and cannot solely or primarily create adverse employment action. | D29: Participant terms, system labels, manager training, review and audit. | E29: Executive Sponsor / HR | F29: Yes | G29: Approved protocol and decision audit. | H29: Draft Ready | I29: Unvalidated pilot harm.
A30: GOV-026 | B30: Incident and stop control | C30: DPO, CISO and executive sponsor can pause affected capture or the pilot when blocking criteria occur. | D30: Agent disable, feature flags, containment, notification, evidence preservation and decision log. | E30: CISO / DPO / Executive Sponsor | F30: Yes | G30: Incident exercise. | H30: Draft Ready | I30: Continued harmful processing.

Sheet Risk Register
A1: Programme Risk Register
A2: Leadership-level risks. The Foundation Threats sheet contains the deeper scenario/control model. Scores use 1–5 likelihood and impact.
A4: Risk ID | B4: Risk | C4: Category | D4: Likelihood | E4: Impact | F4: Inherent score | G4: Primary mitigation | H4: Accountable owner | I4: Relevant stage | J4: Status | K4: Residual target | L4: Trigger / escalation | M4: Next review date
A5: R-001 | B5: Employees experience the product as punitive surveillance, reducing trust, retention and data quality. | C5: Trust / Adoption | D5: 4 | E5: 5 | F5: =D5*E5 -> 20 | G5: Employee value proposition; worker consultation; own evidence/corrections; pilot protection; no activity scores; manager training. | H5: Executive Sponsor / HR / Product | I5: 0–12 | J5: Open | K5: 8 | L5: Material negative trust shift, high opt-out/complaint rate or repeated manager misuse. | M5: 46255
A6: R-002 | B6: Passwords, secrets, customer data or private content are retained or uploaded. | C6: Privacy / Security | D6: 4 | E6: 5 | F6: =D6*E6 -> 20 | G6: Secure-field blocking; exclusions; local redaction; short retention; DLP tests; emergency stop. | H6: CISO / DPO / Desktop | I6: 0,3–12 | J6: Open | K6: 5 | L6: Any known secret or unauthorised private-content retention is pilot blocking. | M6: 46255
A7: R-003 | B7: AI task/idle/capability finding is wrong and harms an employee. | C7: AI / Employment | D7: 4 | E7: 5 | F7: =D7*E7 -> 20 | G7: Evidence hierarchy; confidence; alternatives; employee correction; qualified human review; no solely automated consequential decision. | H7: AI Governance / HR / DPO | I7: 0,7–12 | J7: Open | K7: 8 | L7: High-confidence unsupported allegation, material dispute overturn or subgroup error. | M7: 46255
A8: R-004 | B8: Legal basis, employment documentation or local monitoring requirements are unresolved. | C8: Legal / Regulatory | D8: 3 | E8: 5 | F8: =D8*E8 -> 15 | G8: Full DPIA; UK and Pakistan counsel; policy/notice; consultation; jurisdiction packs; controlled pilot. | H8: Legal / DPO | I8: 0–12 | J8: Open | K8: 5 | L8: Counsel/DPO advises hold or residual high risk is unaccepted. | M8: 46255
A9: R-005 | B9: Managers or administrators misuse raw evidence outside an approved purpose. | C9: Governance / Insider | D9: 3 | E9: 5 | F9: =D9*E9 -> 15 | G9: Summary-first UX; purpose/task/time access; JIT approval; separation of duties; immutable access audit and sanctions. | H9: CISO / HR / DPO | I9: 0,10–12 | J9: Open | K9: 6 | L9: Unauthorised access, repeated curiosity browsing or unreviewed live surveillance. | M9: 46255
A10: R-006 | B10: Device agent introduces unacceptable latency, CPU, memory, battery or stability impact. | C10: Endpoint / Technical | D10: 4 | E10: 4 | F10: =D10*E10 -> 16 | G10: Native/event-driven design; adaptive throttling; performance budgets; application compatibility matrix; kill switch. | H10: Desktop Lead / SRE | I10: 3–12 | J10: Open | K10: 6 | L10: Perceptible input latency, typical CPU above target or critical app instability. | M10: 46255
A11: R-007 | B11: Endpoint agent or update channel becomes a high-privilege compromise path. | C11: Security / Supply Chain | D11: 3 | E11: 5 | F11: =D11*E11 -> 15 | G11: Least privilege; signing/notarisation; SBOM; dependency scanning; staged updates; attestation; rollback; signing-key controls. | H11: CISO / DevSecOps / Desktop | I11: 3–12 | J11: Open | K11: 5 | L11: Critical endpoint finding or update-signing incident. | M11: 46255
A12: R-008 | B12: Human, AI-agent and automation provenance remains incomplete or inaccurate. | C12: Product / AI | D12: 4 | E12: 4 | F12: =D12*E12 -> 16 | G12: Official hooks; process/file correlation; event sequencing; authoritative artefacts; confidence/unknown class; labelled evaluation. | H12: AI Integrations / Data | I12: 6–12 | J12: Open | K12: 8 | L12: Attribution accuracy below pilot threshold or repeated mixed-origin errors. | M12: 46255
A13: R-009 | B13: Task Assurance rewards a preferred process instead of valid outcomes and evidence. | C13: Product / Fairness | D13: 3 | E13: 5 | F13: =D13*E13 -> 15 | G13: Task contracts with multiple valid methods; outcome/quality gates; employee explanation; domain reviewer; deterministic evidence. | H13: Product / Domain Reviewers | I13: 2,7–12 | J13: Open | K13: 6 | L13: Novel but valid work method receives repeated negative findings. | M13: 46255
A14: R-010 | B14: Capability model overstates certainty, treats one task as proof or implies deception. | C14: Capability / Employment | D14: 4 | E14: 5 | F14: =D14*E14 -> 20 | G14: Repeated context-qualified evidence; neutral claim-discrepancy states; confidence/recency/contradiction; human review and appeal. | H14: Capability Lead / HR / DPO | I14: 2,8–12 | J14: Open | K14: 6 | L14: Permanent capability or honesty label from insufficient evidence. | M14: 46255
A15: R-011 | B15: Accessibility accommodations, deep thinking, research or collaboration are misclassified. | C15: Fairness / Inclusion | D15: 3 | E15: 5 | F15: =D15*E15 -> 15 | G15: Outcome over activity; accommodation context; reading/review/collaboration classes; accessibility review; subgroup error tests. | H15: HR / Product / DPO | I15: 0,7–12 | J15: Open | K15: 5 | L15: Disproportionate errors or employee evidence of accommodation-related harm. | M15: 46255
A16: R-012 | B16: Skill Forge introduces a harmful, biased, insecure or confidential-data-leaking update. | C16: AI Platform / Governance | D16: 3 | E16: 5 | F16: =D16*E16 -> 15 | G16: Proposal-only observation; evaluation; expert/security/DPO review; internal/open classification; canary; rollback. | H16: AI Platform / Governance | I16: 11–12 | J16: Open | K16: 6 | L16: Regression, policy violation, confidential leakage or failed rollback. | M16: 46255
... A26: R-022 | B26: Product provides reports but fails to produce measurable employee learning or task-quality improvement. | C26: Product / Commercial | D26: 3 | E26: 5 | F26: =D26*E26 -> 15 | G26: Employee-benefit KPIs; coaching experiments; applied-learning verification; manager and employee qualitative evidence; stop/modify decision. | H26: Product / L&D / Executive Sponsor | I26: 9–12 | J26: Open | K26: 8 | L26: No measurable reduction in rework/gaps or low employee usefulness after controlled trial. | M26: 46255

Sheet KPI Dashboard
A1: Programme KPI Dashboard
A2: Formula-driven programme summary. Foundation readiness reflects draft maturity and outstanding gate conditions; it is not a legal or leadership approval. Gate-readiness percentages measure specification/gate-criteria completeness only — not implementation progress; backlog maturity reflects actual execution status.
A4: Programme metric | B4: Value | C4: Column1 | D4: Stage | E4: Stage name | F4: Effort PW
A5: Total stages | B5: =COUNTA('Delivery Stages'!A5:A18) -> 14 | D5: ='Delivery Stages'!A5 -> 0 | E5: ='Delivery Stages'!B5 -> Foundation — charter, governance and legal boundary | F5: ='Delivery Stages'!N5 -> 16
A6: Total planned duration weeks | B6: =SUM('Delivery Stages'!D5:D18) -> 67 | D6: ='Delivery Stages'!A6 -> 1 | E6: ='Delivery Stages'!B6 -> Foundation — market validation and reference architecture | F6: ='Delivery Stages'!N6 -> 20
A7: Indicative total effort person-weeks | B7: =SUM('Delivery Stages'!N5:N18) -> 602 | D7: ='Delivery Stages'!A7 -> 2 | E7: ='Delivery Stages'!B7 -> Role capability and task contract ontology | F7: ='Delivery Stages'!N7 -> 21
A8: Critical-priority stages | B8: =COUNTIF('Delivery Stages'!J5:J18,"Critical") -> 9 | D8: ='Delivery Stages'!A8 -> 3 | E8: ='Delivery Stages'!B8 -> Device agent foundation | F8: ='Delivery Stages'!N8 -> 40
A9: High-risk stages | B9: =COUNTIF('Delivery Stages'!K5:K18,"High") -> 13 | D9: ='Delivery Stages'!A9 -> 4 | E9: ='Delivery Stages'!B9 -> Telemetry ingestion and evidence storage | F9: ='Delivery Stages'!N9 -> 28
A10: Stage 0 workplan maturity | B10: ='Foundation Dashboard'!B6 -> 0.65294118 | D10: ='Delivery Stages'!A10 -> 5 | E10: ='Delivery Stages'!B10 -> Universal capture MVP | F10: ='Delivery Stages'!N10 -> 54
A11: Stage 1 workplan maturity | B11: ='Foundation Dashboard'!B7 -> 0.71212121 | D11: ='Delivery Stages'!A11 -> 6 | E11: ='Delivery Stages'!B11 -> Development semantics and AI-agent adapters | F11: ='Delivery Stages'!N11 -> 54
A12: Stage 0 gate readiness | B12: ='Foundation Dashboard'!B8 -> 0.57222222 | D12: ='Delivery Stages'!A12 -> 7 | E12: ='Delivery Stages'!B12 -> Provenance and Task Assurance Engine | F12: ='Delivery Stages'!N12 -> 70
A13: Stage 1 gate readiness | B13: ='Foundation Dashboard'!B9 -> 0.56666667 | D13: ='Delivery Stages'!A13 -> 8 | E13: ='Delivery Stages'!B13 -> Capability Graph and baseline assessment | F13: ='Delivery Stages'!N13 -> 40
A14: Mandatory gate blockers/not-started | B14: ='Foundation Dashboard'!B10 -> 5 | D14: ='Delivery Stages'!A14 -> 9 | E14: ='Delivery Stages'!B14 -> Growth Coach and learning loop | F14: ='Delivery Stages'!N14 -> 40
A15: Open programme risks | B15: =COUNTIF('Risk Register'!J5:J26,"Open")+COUNTIF('Risk Register'!J5:J26,"Mitigating") -> 22 | D15: ='Delivery Stages'!A15 -> 10 | E15: ='Delivery Stages'!B15 -> Employee and manager experiences | F15: ='Delivery Stages'!N15 -> 45
A16: High/critical inherent programme risks | B16: =COUNTIF('Risk Register'!F5:F26,">=15") -> 19 | D16: ='Delivery Stages'!A16 -> 11 | E16: ='Delivery Stages'!B16 -> Skill Forge and governed self-improvement | F16: ='Delivery Stages'!N16 -> 48
A17: Residual high/critical foundation threats | B17: =COUNTIF('Foundation Threats'!K5:K34,">=15") -> 0 | D17: ='Delivery Stages'!A17 -> 12 | E17: ='Delivery Stages'!B17 -> Security hardening, internal pilot and rollout decision | F17: ='Delivery Stages'!N17 -> 96
A18: Open assumptions/questions | B18: =COUNTIF('Assumptions Questions'!H5:H44,"Open")+COUNTIF('Assumptions Questions'!H5:H44,"Assumed")+COUNTIF('Assumptions Questions'!H5:H44,"Draft decision") -> 40
A19: Architecture decisions accepted/in-principle | B19: =COUNTIF('Architecture Decisions'!C5:C26,"Accepted in principle")+COUNTIF('Architecture Decisions'!C5:C26,"Accepted") -> 20
A20: Registered research sources | B20: =COUNTA('Source Register'!A5:A200) -> 164
A24: Leadership interpretation and decision rules | D24: Stage 2–3 metric | E24: Value | F24: Interpretation
A25: # | B25: Decision rule | D25: Stage 2 gate readiness | E25: ='Stage 2-3 Dashboard'!B5 -> 0.75714286 | F25: Ontology specification readiness; formal approval pending.
A26: 1 | B26: Foundation drafting is complete; Stage 0 remains unapproved until DPIA/DPO, legal, worker consultation, security and executive decisions are recorded. | D26: Stage 3 gate readiness | E26: ='Stage 2-3 Dashboard'!B6 -> 0.73333333 | F26: Device-agent foundation readiness; code implementation pending.
A27: 2 | B27: Stage 1 remains unapproved until formal licence, platform inventory, cost, resourcing and Architecture Board decisions are recorded. | D27: Stage 2 backlog maturity | E27: ='Stage 2-3 Dashboard'!B7 -> 0 | F27: Backlog is not started; specs are drafted.
A28: 3 | B28: Stage 2 and Stage 3 prompts are ready and may be mobilised conditionally, but implementation involving employee monitoring must not bypass Stage 0 conditions. | D28: Stage 3 backlog maturity | E28: ='Stage 2-3 Dashboard'!B8 -> 0 | F28: Backlog is not started; specs are drafted.
A29: 4 | B29: Build the proprietary evidence/provenance, Task Assurance, Capability Graph, Growth Coach and Skill Forge layers; reuse standards and HumanOS foundation services. | D29: Stage 2 sources | E29: ='Stage 2-3 Dashboard'!B13 -> 12 | F29: Stage-specific sources.
A30: 5 | B30: Do not measure productivity through click, keystroke, code-volume or hours alone. Use task outcomes, quality, independence, context and employee response. | D30: Stage 3 sources | E30: ='Stage 2-3 Dashboard'!B14 -> 20 | F30: Stage-specific sources.
A31: 6 | B31: Keep operational observability separate from sensitive employee evidence; use references and correlation identifiers rather than copying content into traces.
A32: 7 | B32: Pilot success requires employee usefulness and trust evidence as well as capture and model accuracy.
D33: Stage 4–5 metric | E33: Value | F33: Interpretation
D34: Stage 4 gate readiness | E34: ='Stage 4-5 Dashboard'!B5 -> 0.73333333 | F34: Evidence-ingestion/storage specification readiness; implementation and formal approval pending.
D35: Stage 5 gate readiness | E35: ='Stage 4-5 Dashboard'!B6 -> 0.7375 | F35: Universal-capture specification readiness; privacy/performance implementation pending.
D36: Stage 4 backlog maturity | E36: ='Stage 4-5 Dashboard'!B7 -> 0 | F36: Implementation backlog not started.
D37: Stage 5 backlog maturity | E37: ='Stage 4-5 Dashboard'!B8 -> 0 | F37: Implementation backlog not started.
D38: Stage 4 sources | E38: ='Stage 4-5 Dashboard'!B13 -> 15 | F38: Stage-specific primary sources.
D39: Stage 5 sources | E39: ='Stage 4-5 Dashboard'!B14 -> 19 | F39: Stage-specific primary sources.
D42: Stage 6–7 metric | E42: Value | F42: Interpretation
D43: Stage 6 gate readiness | E43: ='Stage 6-7 Dashboard'!B5 -> 0.72 | F43: Semantic-adapter specification readiness; implementation and formal approval pending.
D44: Stage 7 gate readiness | E44: ='Stage 6-7 Dashboard'!B6 -> 0.73333333 | F44: Provenance/Task Assurance specification readiness; evaluation and formal approval pending.
D45: Stage 6 backlog maturity | E45: ='Stage 6-7 Dashboard'!B7 -> 0 | F45: Adapter implementation backlog not started.
D46: Stage 7 backlog maturity | E46: ='Stage 6-7 Dashboard'!B8 -> 0 | F46: Task-assurance implementation backlog not started.
D47: Stage 6–7 sources | E47: ='Stage 6-7 Dashboard'!B12 -> 16 | F47: Stage-specific primary sources.
D48: Evaluation cases | E48: ='Stage 6-7 Dashboard'!B15 -> 20 | F48: Initial labelled dataset cases specified.
D51: Stage 8–9 metric | E51: Value | F51: Interpretation
D52: Stage 8 gate readiness | E52: ='Stage 8-9 Dashboard'!B5 -> 0.72857143 | F52: Capability Graph specification readiness; implementation, calibration and formal approval pending.
D53: Stage 9 gate readiness | E53: ='Stage 8-9 Dashboard'!B6 -> 0.74285714 | F53: Growth Coach specification readiness; safety/usefulness implementation and formal approval pending.
D54: Stage 8 backlog maturity | E54: ='Stage 8-9 Dashboard'!B7 -> 0 | F54: Capability implementation backlog not started.
D55: Stage 9 backlog maturity | E55: ='Stage 8-9 Dashboard'!B8 -> 0 | F55: Coaching/learning implementation backlog not started.
D56: Stage 8–9 sources | E56: ='Stage 8-9 Dashboard'!B12 -> 23 | F56: Current framework, learning and coaching sources.
D57: Effectiveness metrics | E57: ='Stage 8-9 Dashboard'!B18 -> 22 | F57: System-quality and applied-learning measures specified.
D60: Stage 10–11 metric | E60: Value | F60: Interpretation
D61: Stage 10 gate readiness | E61: ='Stage 10-11 Dashboard'!B5 -> 0.74444444 | F61: Human experience specification readiness; implementation, accessibility and formal approval pending.
D62: Stage 11 gate readiness | E62: ='Stage 10-11 Dashboard'!B6 -> 0.74444444 | F62: Skill Forge specification readiness; supply-chain/evaluation implementation and formal approval pending.
D63: Stage 10 backlog maturity | E63: ='Stage 10-11 Dashboard'!B7 -> 0 | F63: Experience implementation backlog not started.
D64: Stage 11 backlog maturity | E64: ='Stage 10-11 Dashboard'!B8 -> 0 | F64: Skill Forge implementation backlog not started.
D65: Stage 10–11 sources | E65: ='Stage 10-11 Dashboard'!B12 -> 30 | F65: Current accessibility, governance, agent-skill, supply-chain and progressive-delivery sources.
D66: User journeys / lifecycle states | E66: ='Stage 10-11 Dashboard'!B17+'Stage 10-11 Dashboard'!B20 -> 36 | F66: End-to-end experience journeys and Skill Forge lifecycle states specified.
D69: Architecture Amendment A-01 | E69: Value | F69: Interpretation
D70: A-01 gate readiness | E70: ='AI Amendment Dashboard'!B5 -> 0.7 | F70: Specification readiness; owner decisions and formal approval remain.
D71: A-01 backlog maturity | E71: ='AI Amendment Dashboard'!B6 -> 0.036363636 | F71: Only documentation task is draft complete; engineering work remains.
D72: Critical open risks | E72: ='AI Amendment Dashboard'!B10 -> 5 | F72: Must be mitigated/accepted before Stage 12 execution.
D73: Task profiles | E73: ='AI Amendment Dashboard'!B11 -> 15 | F73: Initial Work Intelligence model-use purposes.
D74: Qualification controls | E74: ='AI Amendment Dashboard'!B13 -> 25 | F74: HumanOS-specific evaluation areas.
D75: Hybrid test scenarios | E75: ='AI Amendment Dashboard'!B14 -> 18 | F75: Central, standalone, endpoint and no-AI cases.
D78: Stage 12 metric | E78: Value | F78: Interpretation
D79: Stage 12A plan readiness | E79: ='Stage 12 Dashboard'!B5 -> 1 | F79: Final hardening/qualification plan completeness.
D80: Stage 12A execution readiness | E80: ='Stage 12 Dashboard'!B6 -> 0.11111111 | F80: Actual implemented/tested hardening evidence.
D81: Stage 12B plan readiness | E81: ='Stage 12 Dashboard'!B7 -> 1 | F81: Pilot and decision plan completeness.
D82: Stage 12B execution readiness | E82: ='Stage 12 Dashboard'!B8 -> 0 | F82: Actual pilot evidence and decisions.
D83: Stage 12 backlog maturity | E83: ='Stage 12 Dashboard'!B9 -> 0.034285714 | F83: Engineering/pilot work completion.
D84: Critical open risks | E84: ='Stage 12 Dashboard'!B11 -> 4 | F84: Unresolved critical final-stage risks.
D85: Qualification runs | E85: ='Stage 12 Dashboard'!B13 -> 12 | F85: Planned development and production task × effort evaluations.
D86: Pilot metrics with actuals | E86: ='Stage 12 Dashboard'!B16 -> 0 | F86: Metrics populated after execution.
D89: Stage 12A repository assessment | E89: Value | F89: Interpretation
D90: Current code alignment | E90: ='Stage 12A Repo Assessment'!B5 -> 0.25384615 | F90: Static code/architecture alignment with A-01 target.
D91: Critical audit findings | E91: ='Stage 12A Repo Assessment'!B7 -> 17 | F91: Must be remediated and dynamically tested.
D92: P0 remediation items | E92: ='Stage 12A Repo Assessment'!B8 -> 15 | F92: Required before model qualification or employee pilot.
D93: Development AI readiness | E93: ='Stage 12A Repo Assessment'!B13 -> 0.04 | F93: Fable/Opus/Codex implementation and qualification readiness.
D94: Stage 12A controls passed | E94: ='Stage 12A Hardening Gate'!M8 -> 0 | F94: Actual gate controls passed or waived; currently zero.

Sheet Source Register
A1: Source Register
A2: Primary and high-value research sources used for the Stage 0–1 foundation package. Sources support planning decisions but do not replace Nessovo legal, security, architecture or procurement approvals.
A4: Source ID | B4: Source / publisher | C4: Type | D4: Supports | E4: Source URL | F4: Priority | G4: Review note / status
A5: SRC-001 | B5: OpenAI — Prompt engineering best practices | C5: Official guidance | D5: Instructions first, delimiters, specificity, output examples and iterative refinement. | E5: https://help.openai.com/en/articles/6654000-best-practices-for-prompt-engineering-with-the-openai-api | F5: High | G5: Used in Master Prompts.
A6: SRC-002 | B6: OpenAI — Prompt engineering best practices for ChatGPT | C6: Official guidance | D6: Clear task, context, format, iterative refinement and examples. | E6: https://help.openai.com/en/articles/10032626-prompt-engineering-best-practices | F6: High | G6: Used in Master Prompts.
A7: SRC-003 | B7: Google Gemini — Prompting strategies | C7: Official guidance | D7: Precise instructions, consistent structure, decomposition, planning and validation. | E7: https://ai.google.dev/gemini-api/docs/prompting-strategies | F7: High | G7: Used in Master Prompts.
A8: SRC-004 | B8: GitHub Copilot — Prompt engineering concepts | C8: Official guidance | D8: Break down complex tasks, provide context/examples and validate outputs. | E8: https://docs.github.com/en/enterprise-cloud@latest/copilot/concepts/prompting/prompt-engineering | F8: High | G8: Used in Master Prompts.
A9: SRC-005 | B9: GitHub Copilot — Best practices | C9: Official guidance | D9: Specific prompts, task decomposition, context and output review. | E9: https://docs.github.com/en/copilot/get-started/best-practices | F9: High | G9: Used in Master Prompts.
A10: SRC-006 | B10: Teramind employee monitoring | C10: Commercial product | D10: Market baseline for screen, keystroke, application/web and active/idle monitoring. | E10: https://www.teramind.co/solutions/employee-monitoring/ | F10: High | G10: Benchmark only; not recommended as product core.
A11: SRC-007 | B11: Teramind live desktop/history playback | C11: Commercial product | D11: Live view and historical screen playback capability. | E11: https://www.teramind.co/features/live-desktop-view-history-playback/ | F11: Medium | G11: Raw monitoring baseline.
A12: SRC-008 | B12: ActivTrak AI Insights | C12: Commercial product | D12: AI-tool adoption, workforce analytics and productivity-impact reporting. | E12: https://support.activtrak.com/hc/en-us/articles/50125731483675-AI-Insights-Add-on | F12: High | G12: Reporting/market signal.
A13: SRC-009 | B13: UiPath Task Capture settings | C13: Commercial documentation | D13: Screenshots around clicks/keyboard actions, UI elements and task capture. | E13: https://docs.uipath.com/task-capture/standalone/2021.10/user-guide/capture-settings | F13: High | G13: Action-level capture reference.
A14: SRC-010 | B14: UiPath Task Mining | C14: Commercial documentation | D14: Task-mining projects and process discovery. | E14: https://docs.uipath.com/process-mining/automation-cloud/latest/user-guide/starting-a-task-mining-project-from-process-mining | F14: High | G14: Process/task mining reference.
A15: SRC-011 | B15: ABBYY Timeline Task Mining | C15: Commercial documentation | D15: Screen snapshots, clicks, text entered, applications and task association. | E15: https://help.abbyy.com/en-us/timeline/6/user_guide/task-mining | F15: High | G15: Task reconstruction reference.
... A170: SRC-164 | B170: Project AI Assistant direct Anthropic path | C170: Internal code | D170: Direct provider call remains outside central gateway. | E170: https://github.com/Rapidtackltd/humanos-backend-services/blob/79a38ade1fc0163cadf39ae3cccd466b7f8d5d9d/project-service-be/Project-Service-BE/src/main/java/com/humanos/projects/service/AIAssistantService.java | F170: Critical | G170: Monorepo cutover.

Sheet Master Prompts
A1: Master Prompts — Foundation and Next-Stage Execution
A2: Research-backed prompts used to execute the combined Stage 0–1 foundation workstream, followed by reusable prompts for Stages 2 and 3.
A4: ID | B4: Prompt-design principle | C4: Why it matters | D4: Primary basis | E4: Decision | F4: Source URL
A5: P-01 | B5: Put critical instructions and constraints first. | C5: Reduces missed requirements and establishes the operating frame before context. | D5: OpenAI / Google | E5: Adopted | F5: https://help.openai.com/en/articles/6654000-best-practices-for-prompt-engineering-with-the-openai-api
A6: P-02 | B6: Separate role, context, task, constraints and output using consistent delimiters. | C6: Makes long, multi-disciplinary prompts easier to parse and audit. | D6: OpenAI / Google | E6: Adopted | F6: https://ai.google.dev/gemini-api/docs/prompting-strategies
A7: P-03 | B7: Define the required result, format, detail level and decision criteria explicitly. | C7: Prevents generic narrative output and forces decision-ready deliverables. | D7: OpenAI | E7: Adopted | F7: https://help.openai.com/en/articles/10032626-prompt-engineering-best-practices
A8: P-04 | B8: Break complex work into chained stages and make outputs from one stage inputs to the next. | C8: Improves reliability for research, architecture, governance and delivery planning. | D8: Google / GitHub | E8: Adopted | F8: https://docs.github.com/en/enterprise-cloud@latest/copilot/concepts/prompting/prompt-engineering
A9: P-05 | B9: Provide examples, schemas or expected output structures. | C9: Makes generated work easier to validate and transfer into Excel or implementation artefacts. | D9: OpenAI / GitHub | E9: Adopted | F9: https://docs.github.com/en/copilot/get-started/best-practices
A10: P-06 | B10: Require source grounding and distinguish fact, inference, assumption and recommendation. | C10: Reduces unsupported claims and creates an auditable research trail. | D10: Nessovo control | E10: Adopted | F10: Internal project requirement
A11: P-07 | B11: Plan, execute and validate against explicit acceptance criteria. | C11: Adds a completion check instead of treating first-pass generation as final. | D11: Google / GitHub | E11: Adopted | F11: https://ai.google.dev/gemini-api/docs/prompting-strategies
A12: P-08 | B12: State prohibited outputs and the required alternative behaviour. | C12: Prevents the prompt from drifting into surveillance scoring or unsupported employment conclusions. | D12: OpenAI / Nessovo | E12: Adopted | F12: https://help.openai.com/en/articles/6654000-best-practices-for-prompt-engineering-with-the-openai-api
A17: Applied Stage 0–1 Master Prompt
A18: Prompt section | B18: Exact instruction | C18: Purpose
A19: <identity> | B19: You are an integrated senior delivery team comprising: a product strategist, enterprise architect, Java/Spring platform architect, Python/AI architect, native desktop-agent architect, data architect, security architect, privacy engineer, UK employment/privacy specialist, HR and learning-design specialist, AI evaluation lead, programme manager and employee-experience representative. Work as one team. Resolve conflicts by prioritising lawful and safe operation, factual evidence, employee fairness, HumanOS platform fit, technical feasibility and commercial differentiation—in that order. | C19: Defines the cross-functional decision authority.
A20: <mission> | B20: Create the complete decision-ready foundation for Nessovo HumanOS Work Intelligence by executing Stage 0 and Stage 1 as one combined Foundation & Validation workstream while retaining two independent approval gates. Stage 0 establishes purpose, scope, governance, lawful boundaries, employee rights and pilot authority. Stage 1 validates the market and open-source landscape, makes build/buy/integrate/defer decisions, and defines the HumanOS reference architecture and technical-spike plan. | C20: Establishes the exact objective and the relationship between both stages.
A21: <authoritative_context> | B21: Company: Nessovo. Platform: HumanOS, an existing microservices-based modular platform intended to support business verticals and long-term human development. Existing foundation services should be reused wherever they meet the requirement. Primary backend technologies are Java and Spring Boot; Python is used for AI, multimodal analysis, scoring and evaluation services. Native OS components may use Rust, Swift, C#, C++ or platform APIs where Java/Python are unsuitable. Target product: a task-aware work-intelligence system that records and reconstructs material activity on company-managed computers; links work to assigned tasks and acceptance criteria; distinguishes human, AI-agent, automation and system actions; evaluates task completion and quality; verifies evidence of role capability; provides employee coaching and training; gives authorised managers evidence-linked reports; and improves HumanOS skills and evaluators through a governed learning loop. Initial vertical: AI-assisted software development. Future design must support other HumanOS business verticals without forcing every domain into software-development semantics. | C21: Provides stable product and platform context.
A22: <definitions> | B22: Use these definitions consistently: - FACT: directly supported by a primary source or observed repository artefact. - INFERENCE: a reasoned conclusion derived from identified facts. - RECOMMENDATION: a proposed Nessovo decision. - ASSUMPTION: an unresolved condition used temporarily and explicitly. - ACTIVITY EVIDENCE: captured events or artefacts; not automatically a performance conclusion. - TASK ASSURANCE: evaluation against an approved Task Execution Contract and acceptance criteria. - CAPABILITY EVIDENCE: repeated, context-qualified evidence that a person can perform a defined capability at a defined autonomy level. - CONSEQUENTIAL DECISION: a decision affecting dismissal, discipline, pay, promotion, probation or equivalent employment outcome. - FOUNDATION GATE: a formal approve, conditional approve, hold or reject decision with named authority and evidence. | C22: Prevents ambiguous terminology.
A23: <research_protocol> | B23: 1. Search current primary sources first: official product documentation, regulator/government guidance, standards bodies, authoritative project documentation, GitHub README files, licence files, releases and architecture documents. 2. Record source URL, publisher/project, retrieval date, what the source proves, limitations, licence status and relevance to Nessovo. 3. For GitHub projects, inspect project maturity, architecture, platform support, data captured, local/cloud model, extensibility, licence and commercial-use constraints. Do not equate public source code with unrestricted commercial reuse. 4. Compare commercial products, process/task-mining platforms, workforce analytics, developer-intelligence tools, skills-intelligence platforms, workflow-record/replay systems and AI-agent observability. 5. Separate facts, inferences, recommendations and assumptions in every decision. 6. Where sources disagree or a conclusion is uncertain, record the disagreement and propose a validation spike. 7. Do not claim that no comparable product exists. State precisely which capability combination remains differentiated. | C23: Defines evidence quality and research discipline.
A24: <stage_0_workstream> | B24: Produce: A. Product charter, strategic positioning and initial vertical. B. Allowed uses, prohibited uses and non-goals. C. Purpose-by-data-type necessity and proportionality matrix. D. Governance model: worker transparency, consultation, evidence access, corrections, disputes, meaningful human review, manager decision rights and audit. E. DPIA initiation pack and legal-question register for UK and Pakistan/Lahore deployment; identify where jurisdiction-specific counsel is required. F. Security and privacy principles: secure-field blocking, application/domain exclusions, edge redaction, encryption, retention, access purpose codes and incident handling. G. Stakeholder map and RACI. H. Internal pilot definition, participant protection, success metrics, stop criteria and approval requirements. I. Stage 0 gate checklist with approve/conditional/hold/reject criteria. | C24: Stage 0 deliverable contract.
A25: <stage_1_workstream> | B25: Produce: A. Market landscape and strategic gap analysis. B. GitHub/open-source scan with licence and maturity notes. C. Component-level build/buy/integrate/benchmark/defer decisions. D. Reference architecture aligned to HumanOS. E. Initial bounded contexts and deployment boundaries; avoid premature nano-services. F. Technology decisions for Java/Spring, Python AI services, native device agent, Kafka-compatible event streaming, CloudEvents-style envelopes, schema governance, OPA-style policy-as-code and OpenTelemetry operational/AI traces. G. Data architecture for transactional metadata, evidence objects, search, embeddings and graph queries; defer specialised stores until proven necessary. H. Architecture decision record register. I. Device-agent, privacy, performance, provenance and AI-evaluation technical spikes. J. Stage 1 gate checklist with architecture, licence, threat, cost, ownership and feasibility criteria. | C25: Stage 1 deliverable contract.
A26: <architecture_constraints> | B26: 1. Reuse HumanOS identity, organisation, task/project, workflow, policy, audit, notification, secrets, object/file, model-gateway and event capabilities where suitable. 2. Keep the desktop/device agent separate from cloud business services. 3. Use Java/Spring Boot for durable domain services, API orchestration, policy integration, audit and transactional workflows. 4. Use Python for multimodal interpretation, episode classification, task/capability evaluators, coaching, embeddings and evaluation harnesses. 5. Use native code only for OS capture, secure local storage, permissions, accessibility and performance-critical device functions. 6. Use event-driven contracts with idempotency, signed batches, tenant partitioning, schema versioning and replay. 7. OpenTelemetry is for service and AI operational observability; raw worker evidence and model content must not be copied into traces by default. 8. Start with PostgreSQL and object storage; use pgvector/search as justified; introduce a dedicated graph database only after query and scale evidence. 9. Reuse the HumanOS workflow runtime before introducing another orchestrator. 10. For Java baseline: retain the existing supported HumanOS version unless a measured migration case is approved. For greenfield-compatible services, benchmark Java 25 LTS with Spring Boot 4.1 and the compatible Spring Cloud release train. 11. Every service boundary must have a security, scale, ownership or transactional justification. | C26: Prevents architecture drift and technology novelty bias.
A27: <governance_constraints> | B27: The product must not: - operate as a hidden general-surveillance system; - use click, mouse or keystroke volume as a productivity score; - infer emotions, personality, honesty or mental state from activity; - capture password or known secure-field content; - make solely automated consequential employment decisions; - present uncertain AI classifications as facts; - let managers browse raw evidence without role, purpose, scope and audit controls; - repurpose evidence beyond the approved purpose without a new assessment; - penalise legitimate thinking, reading, accessibility accommodations, meetings or automated execution waits. The product must provide visible monitoring status, employee access to their evidence, correction and dispute routes, confidence and source links, meaningful human review, local minimisation/redaction and jurisdiction-specific policies. | C27: Non-negotiable safety and trust boundary.
A28: <required_deliverables> | B28: Create and populate: 1. Master prompt and prompt-research principles. 2. Foundation dashboard. 3. Detailed Stage 0–1 workplan. 4. Product Charter v1. 5. Purpose Policy Matrix. 6. Stakeholder RACI. 7. Expanded market landscape and GitHub scan. 8. Strategic gap matrix. 9. Build/Buy/Integrate decision matrix. 10. Reference architecture. 11. Architecture decision register. 12. Stage 0–1 gate checklists. 13. Assumptions and open-question register. 14. Foundation threat register. 15. Pilot definition. 16. Updated delivery stages, microservices map, governance, risk, KPIs and source register. 17. Exact execution prompts for Stage 2 and Stage 3. | C28: Makes the output verifiable.
A29: <excel_output_contract> | B29: Use a professional Excel workbook as the system of record. Each researched row must contain a source URL. Each action must have an ID, owner role, dependency, priority, status, effort, deliverable and acceptance criterion. Each decision must record status, rationale, alternatives, risk and revisit trigger. Use formulas for readiness and completion metrics. Apply consistent status values and conditional formatting. Keep raw approvals and organisational decisions marked as pending where they have not actually occurred. Never present a drafted artefact as legally approved or leadership-approved. | C29: Defines spreadsheet semantics and honesty requirements.
... A32: <completion_criteria> | B32: Stage 0–1 foundation work is complete as a draft package when all required workbook sections are populated, sources are registered, architecture and build/buy recommendations are explicit, gate criteria are calculable, unresolved approvals are clearly marked, and the workbook passes formula and visual-quality checks. Stage 0 and Stage 1 are not organisationally approved until the named Nessovo authorities record their decisions. | C32: Separates document completion from real approval.
A35: Next Execution Prompt — Stage 2
A36: <identity> You are a senior cross-functional team of product architects, organisational psychologists, HR/L&D specialists, domain experts, knowledge-graph engineers, Java/Spring architects, Python/AI engineers, data-governance specialists and employee-experience representatives. </identity> <mission> Execute Stage 2 of Nessovo HumanOS Work Intelligence: design the Role Capability Contract, Task Execution Contract and evidence ontology that will govern how job requirements, employee claims, task evidence, autonomy, quality, training and role readiness are represented. Produce implementation-ready schemas, rubrics, examples, APIs, events, backlog and gate criteria in the existing Excel workbook. </mission> <authoritative_context> Nessovo is building HumanOS as a modular microservices platform. Work Intelligence must support all future business verticals while the first implementation vertical is AI-assisted software development. Java/Spring Boot is the primary durable domain-service stack; Python is used for AI extraction, scoring and evaluation. Existing HumanOS identity, organisation, role, task/project, workflow, policy, audit, notification, model-gateway and event services must be reused. </authoritative_context> <non_negotiable_rules> - A job-description statement is a requirement or claim, not evidence. - A single task failure or success cannot permanently establish capability. - Capability evidence must be context-qualified, confidence-scored, time-aware and linked to inspectable work evidence. - Never classify a claim discrepancy as dishonesty without separate human investigation and evidence. - Capability cannot increase merely because training was completed; it increases after successful application. - Do not infer personality, emotion, protected traits or mental state. - Consequential employment decisions require meaningful human review. - The ontology must support multiple valid work methods and accessibility accommodations. </non_negotiable_rules> <required_workstreams> 1. Define canonical entities and relationships: Role, RoleVersion, Responsibility, Outcome, Capability, CapabilityLevel, BehaviouralIndicator, Tool/Environment, EmployeeClaim, BaselineAssessment, TaskContract, AcceptanceCriterion, QualityGate, EvidenceRequirement, WorkEpisode, Artefact, CapabilityEvidence, Gap, LearningIntervention, ReviewDecision and RoleReadiness. 2. Define capability levels with observable descriptors for knowledge, execution, autonomy, complexity, quality, transfer, recovery and mentoring. 3. Define evidence weighting, confidence, recency, consistency, task difficulty, guidance dependence and contradictory evidence. 4. Define claim statuses and claim-evidence discrepancy workflow. 5. Define Task Execution Contract structure, lifecycle, versioning and approval. 6. Define role-to-task-to-capability traceability. 7. Produce at least four software-development role profiles and twelve representative task contracts with evidence rubrics. 8. Produce domain-neutral extension rules for future HumanOS verticals. 9. Define Java domain models, PostgreSQL logical schema, JSON Schemas, REST/OpenAPI resources and CloudEvents-compatible domain events. 10. Define deterministic rules versus Python/AI-assisted extraction and scoring. 11. Define fairness, human-review, correction, appeal, audit and retention controls. 12. Create a Stage 2 implementation backlog, test/evaluation suite and go/no-go gate. </required_workstreams> <output_contract> Update the workbook with dedicated sheets for ontology, entity dictionary, relationships, capability-level rubric, role templates, task-contract templates, evidence scoring, examples, APIs/events, backlog, risks, decisions, gate and sources. Each row must have IDs, definitions, owner, status, acceptance criteria and source where researched. Distinguish fact, recommendation, assumption and unresolved question. Use formulas for completeness and gate readiness. </output_contract> <validation> Validate that every role requirement can trace to capabilities, every task criterion can trace to evidence, every capability update can trace to multiple qualified evidence items, every AI inference is challengeable, and the model can extend beyond software development without rewriting the core ontology. </validation>
A47: Next Execution Prompt — Stage 3
A48: <identity> You are a senior native-device engineering and platform team comprising Windows, macOS and Linux architects; Rust, Swift, C#/C++ and Java engineers; security and privacy engineers; endpoint-management specialists; performance engineers; QA/SDET leads; threat modellers; HumanOS Spring-platform architects; and employee-experience representatives. </identity> <mission> Execute Stage 3 of Nessovo HumanOS Work Intelligence: design and implement the Device Agent Foundation for company-managed endpoints. The stage must deliver an installable, signed agent skeleton for Windows and macOS, policy synchronisation, explicit work-session controls, secure local journaling, health telemetry, update architecture and a validated technical-spike plan for later capture capabilities. Update the existing Excel workbook with implementation-ready specifications and backlog. </mission> <authoritative_context> The device agent is the universal evidence-collection edge of HumanOS Work Intelligence. It must remain separate from cloud microservices. HumanOS core services use Java/Spring Boot; the native agent may use Rust as the shared core with Swift and Windows-native bridges where required. Python is not the primary always-on capture runtime but may be used in development tools and local model experiments. Stage 3 does not yet implement unrestricted keylogging or complete screenshot capture; it establishes the secure, policy-controlled foundation on which Stage 5 capture will be built. </authoritative_context> <non_negotiable_rules> - No covert mode. - Visible monitoring state and explicit session controls are mandatory. - Password/secure-field blocking and application/domain exclusion architecture must exist before sensitive capture. - The agent must fail safe when policy is unavailable or invalid. - Device credentials and evidence keys must use OS secure storage. - Every event batch must be signed, schema-versioned, idempotent and tenant/device/session scoped. - Local collection must continue safely during temporary network loss. - Software update, rollback, tamper evidence and audit are mandatory. - The agent must not create perceptible keyboard/mouse latency. - Accessibility and employee correction requirements must be included from the beginning. </non_negotiable_rules> <required_workstreams> 1. Produce Windows/macOS/Linux capability and permission matrix; Linux may be deferred with explicit Wayland limitations. 2. Decide shared-core and native-bridge architecture through documented ADRs. 3. Define agent modules: bootstrap, identity/certificates, policy engine/cache, session controller, event journal, encryption/key management, batcher/uploader, health/diagnostics, update/rollback, UI/tray, exclusions, audit and adapter SDK. 4. Define device registration, attestation, certificate rotation, mTLS and revocation. 5. Define local encrypted SQLite/SQLCipher-style journal and content-addressed object cache. 6. Define policy bundle format, signatures, versioning, expiry, offline behaviour and OPA/HumanOS policy integration. 7. Define work-day/task-session state machine and user-visible states. 8. Define event envelope, local sequence numbers, deduplication keys, compression, retry/backoff and telemetry-gap reporting. 9. Define secure update and code-signing pipeline for Windows and macOS. 10. Produce threat model covering agent tampering, privilege escalation, secret capture, malicious updates, evidence exfiltration, spoofed events and insider misuse. 11. Define performance, reliability, storage and battery budgets. 12. Define technical spikes for active window/process, accessibility, secure fields, screenshots, input provenance, file events, browser/native messaging and AI-agent adapters. 13. Produce test strategy: unit, contract, integration, OS-permission, security, performance, chaos/offline, installer/update and employee UX. 14. Produce APIs/events, repository structure, CI/CD plan, implementation backlog, pilot build plan and Stage 3 go/no-go gate. </required_workstreams> <output_contract> Update the workbook with sheets for agent architecture, OS capability matrix, module specification, state machine, security/key model, policy format, event and API contracts, technical spikes, performance budgets, threat model, test matrix, backlog, ADRs, gate and sources. Use Java/Spring contracts for cloud-facing APIs and native/Rust definitions for the agent. Every task requires owner, dependency, effort, deliverable and acceptance criterion. </output_contract> <validation> Validate that the proposed agent can be installed, registered, policy-controlled, started/paused/stopped visibly, operated offline, updated and rolled back without implementing unsafe broad capture. Demonstrate that no future capture component can bypass policy, secure-field exclusion, encryption, signing, audit or employee visibility. </validation>
A62: Next Execution Prompt — Stage 4
A63: <identity> You are a senior HumanOS backend, data-platform, security, SRE, privacy-engineering and evidence-systems team. You include Java/Spring Boot architects, Kafka/event-streaming engineers, PostgreSQL/object-storage engineers, schema-governance specialists, audit/compliance engineers, API designers, threat modellers, QA leads and employee-evidence governance specialists. </identity> <mission> Execute Stage 4 of Nessovo HumanOS Work Intelligence: design and implement the Telemetry Ingestion and Evidence Storage foundation that receives signed endpoint batches, validates schemas, deduplicates/replays events, stores evidence metadata and objects, links audit, and exposes replay/timeline APIs for later Task Assurance and Capability Graph processing. Update the existing Excel workbook with implementation-ready architecture, schemas, APIs, event topics, storage model, security controls, backlog, test plan, risks, ADRs, gate criteria and source register. </mission> <authoritative_context> Nessovo HumanOS uses Java/Spring Boot for durable domain services and Python for AI/evaluation services. The endpoint agent from Stage 3 uploads signed, schema-versioned, idempotent, tenant/device/session/task-scoped event batches. Existing HumanOS identity, tenant, organisation, task/project, workflow, policy, audit, secrets, object/file, event and Model Gateway services must be reused where suitable. Stage 4 is not an AI interpretation stage. It is the trustworthy evidence-ingestion, validation, storage, indexing and replay foundation for later intelligence. </authoritative_context> <non_negotiable_rules> - Do not store raw evidence in operational traces or generic logs. - Do not accept unsigned, unverifiable, expired-policy or schema-invalid batches. - Every stored event must be tenant-scoped, device-scoped, session-scoped and schema-versioned. - Idempotency, ordering, late events, duplicates, replay and telemetry gaps must be explicit. - Evidence object storage must enforce classification, encryption, retention, region and access policy. - Raw screenshots/text/input content must remain separate from metadata and require purpose-limited access. - Every evidence access must be auditable. - Ingestion failure must not silently create false timelines. - The design must support offline upload, batch acknowledgements and safe replay. </non_negotiable_rules> <required_workstreams> 1. Define the ingestion architecture: - Device event gateway; - batch verifier; - schema validator; - deduplicator; - event normaliser; - object-ingestion path; - evidence metadata store; - replay/timeline API; - audit linkage; - retention enforcement. 2. Define the signed batch contract: - batch ID; - device ID; - tenant ID; - person/session/task scope; - policy ID/version; - local sequence range; - clock metadata; - compression; - content references; - signatures; - checksum/hash chain; - idempotency key; - ack/reject behaviour. 3. Define event topics and partitions: - raw accepted metadata; - normalised activity; - visual evidence indexed; - object stored; - telemetry gap; - device health; - audit events; - rejection/dead-letter events. 4. Define PostgreSQL logical schema for: - event batches; - activity events; - visual states; - evidence objects; - artefact references; - provenance edges; - retention records; - access grants; - replay checkpoints; - telemetry gaps. 5. Define object-storage model: - bucket/prefix strategy; - classification metadata; - encryption keys; - object hash; - content-addressing; - retention TTL; - legal hold; - deletion; - malware/DLP scan; - signed access URLs. 6. Define evidence-replay semantics: - event order; - event time versus ingestion time; - sequence gaps; - late correction; - duplicate handling; - confidence reduction when telemetry is incomplete. 7. Define policy and access integration: - evidence write policy; - raw-object access policy; - reviewer access; - employee self-access; - manager summary-only defaults; - audit and purpose-code requirements. 8. Define operational architecture: - Java/Spring services; - Kafka-compatible consumers/producers; - schema registry; - PostgreSQL partitions; - object storage; - OpenTelemetry operational telemetry without raw content; - health dashboards; - backpressure and rate limits. 9. Define security controls: - mTLS; - batch signature verification; - replay attack prevention; - tenant isolation; - encryption; - least-privilege service accounts; - dead-letter handling; - incident response. 10. Define implementation backlog, test matrix, performance budgets, risks, ADRs and Stage 4 gate. </required_workstreams> <output_contract> Update the workbook with dedicated sheets for: 1. Stage 4 Architecture 2. Batch Contract 3. Event Topics 4. Evidence Storage Model 5. Ingestion APIs 6. Replay and Timeline Semantics 7. Retention and Access Controls 8. Stage 4 Backlog 9. Stage 4 Risks 10. Stage 4 ADRs 11. Stage 4 Gate 12. Stage 4 Sources Every row must include IDs, owner, status, acceptance criteria, dependencies and source where applicable. Use formulas for readiness and risk scores. Keep sensitive raw evidence out of general observability and logs. </output_contract> <validation> Validate that the Stage 4 design can: 1. Reject invalid/suspicious batches. 2. Accept valid offline batches idempotently. 3. Preserve event ordering and gaps. 4. Store evidence metadata separately from content. 5. Enforce classification, retention and access policies. 6. Support replay/timeline queries. 7. Provide complete auditability. 8. Avoid false timeline confidence when data is missing. 9. Integrate with existing HumanOS services. 10. Pass formula, source and visual-quality checks. </validation>
A77: Next Execution Prompt — Stage 5
A78: <identity> You are a senior endpoint-capture, privacy-engineering, OS-integration, UX, QA, security, data and AI-evidence team. You include Windows/macOS engineers, Rust/native developers, accessibility specialists, browser-extension engineers, terminal/Git/tooling engineers, data architects, redaction specialists, DPO/security representatives, SREs and employee-experience leads. </identity> <mission> Execute Stage 5 of Nessovo HumanOS Work Intelligence: design and implement the Universal Capture MVP on top of the Stage 3 device-agent foundation and Stage 4 ingestion/evidence storage layer. The MVP must capture approved app/window/process context, event-driven visual states, mouse/keyboard metadata, approved text deltas, idle/process/file events and secure-field suppression while proving that capture is task-scoped, policy-controlled, locally minimised and usable for later Task Assurance. Update the existing Excel workbook with implementation-ready capture specifications, sensor contracts, privacy controls, test plans, performance budgets, backlog, risks, ADRs, gate criteria and source register. </mission> <authoritative_context> Stage 5 depends on: - Stage 2 Task Execution Contract and evidence ontology; - Stage 3 device-agent foundation, policy bundle, state machine, local journal and update model; - Stage 4 ingestion, evidence storage, replay and audit model. Stage 5 is the first universal evidence-capture MVP. It must not become unrestricted surveillance. Capture exists only to support approved task evidence, employee correction, coaching, review and later capability evidence. </authoritative_context> <non_negotiable_rules> - No covert mode. - No full-motion continuous recording as the default. - No password, authentication-code or known secure-field retention. - No raw text capture outside approved controls/surfaces. - No capture outside approved policy, hours, session and task scope. - Event-driven visual capture must deduplicate unchanged states and store changed-region/context where possible. - Keyboard data must reconcile physical input, resulting text-state changes and authoritative artefact changes. - Mouse/click events must not be used as productivity scores. - Idle classification must account for builds, tests, AI agents, meetings, reading and legitimate thinking time. - Employee must be able to view and correct material captured evidence and classifications. </non_negotiable_rules> <required_workstreams> 1. Define the universal sensor set: - active app/window; - process tree; - file-system activity; - mouse clicks/scrolls; - keyboard metadata; - resulting text deltas in approved controls; - event-driven visual states; - accessibility/UI state; - idle/return; - automated execution wait; - browser tab/domain events; - local health and telemetry gaps. 2. Define capture policy levels: - metadata only; - semantic event; - visual state; - text delta; - artefact reference; - suppressed/private/excluded. 3. Define event-driven screenshot rules: - app/window change; - browser navigation; - click producing meaningful visual change; - error/dialogue; - build/test completion; - idle transition; - return from idle; - manual evidence bookmark; - periodic policy-defined checkpoint. 4. Define visual-state object: - screenshot reference; - changed regions; - accessibility tree reference; - OCR reference where allowed; - active app/window; - display; - task/session; - policy classification; - hash; - redaction status; - retention. 5. Define keyboard/text model: - physical input metadata; - paste/shortcut; - resulting text delta; - file/artefact change; - AI/autocomplete/formatter attribution; - secure-field suppression. 6. Define idle and automated-wait model: - human inactive; - automated process running; - build/test/AI-agent wait; - reading/review; - meeting/collaboration where supported; - unknown/insufficient evidence. 7. Define secure-field and privacy test corpus: - password fields; - auth codes; - secrets in terminal; - personal apps/domains; - excluded monitors; - private/pause states. 8. Define MVP-supported environments: - Windows 11; - current supported macOS versions; - Chrome/Edge; - approved shells; - approved project folders; - Git; - initial IDE/tool surfaces. 9. Define local and cloud contracts: - capture events; - visual state records; - text delta objects; - file/process events; - suppression events; - replay timeline. 10. Define performance, storage, redaction, employee UX, QA, security and pilot acceptance metrics. 11. Create implementation backlog, risks, ADRs, tests and Stage 5 gate. </required_workstreams> <output_contract> Update the workbook with dedicated sheets for: 1. Capture MVP Scope 2. Sensor Specifications 3. Visual State Model 4. Input and Text Model 5. Idle and Automation Model 6. Privacy Redaction Tests 7. Supported Environment Matrix 8. Capture Event Contracts 9. Stage 5 Backlog 10. Stage 5 Risks 11. Stage 5 ADRs 12. Stage 5 Gate 13. Stage 5 Sources Every row must include unique ID, owner, dependency, status, acceptance criteria, privacy/security impact and source where applicable. Use formulas for readiness, risk and acceptance target tracking. </output_contract> <validation> Validate that Stage 5 can: 1. Capture app/window/process context accurately. 2. Link clicks to visual states. 3. Capture approved text deltas without secure-field leakage. 4. Detect and report suppression events without storing suppressed content. 5. Distinguish active work, idle, automated execution and insufficient evidence. 6. Respect policy/session/task scope. 7. Operate within endpoint performance budgets. 8. Upload events through Stage 4 contracts. 9. Provide employee-visible evidence and correction hooks. 10. Pass formula, source, privacy and visual-quality checks. </validation>
A112: Combined Next Execution Prompt — Stages 6 and 7
A113: <identity> You are one integrated senior delivery team comprising: - developer-platform and IDE-integration architects; - browser-extension and shell/PTY engineers; - Git, GitHub, CI/CD and build-system specialists; - Codex, Claude Code and multi-agent integration engineers; - Java/Spring Boot domain architects; - Python/AI, multimodal and evaluation engineers; - event-streaming and knowledge-graph engineers; - product, QA, security, privacy, HR and employee-experience representatives; - domain expert reviewers for software engineering, QA and DevOps. Work as one team. Execute Stage 6 and Stage 7 as a combined Semantic Integration & Task Assurance workstream, while preserving a separate Stage 6 adapter gate and Stage 7 intelligence gate. </identity> <mission> Execute Stages 6 and 7 of Nessovo HumanOS Work Intelligence. Stage 6 must implement the semantic adapter layer for browser, terminal/shell, Git/GitHub, CI/build/test, IDE/toolchain and AI-agent systems. It must normalise provider/tool-specific events into HumanOS evidence and provenance contracts without making final employment or capability conclusions. Stage 7 must build the evidence-linked Provenance and Task Assurance Engine: work-episode segmentation, human/AI/automation/system causality, task alignment, blocker classification, acceptance-criteria and quality-gate evaluation, task completion assurance, confidence calibration, employee correction and meaningful human review. Update the existing Excel workbook with implementation-ready architecture, contracts, adapters, provenance model, evaluator design, evaluation data, APIs/events, backlog, risks, ADRs, separate Stage 6 and Stage 7 gates, and sources. </mission> <authoritative_context> The following HumanOS foundations already exist in the workbook: - Stage 2: - Role Capability Contract; - Task Execution Contract; - evidence ontology; - capability levels and evidence scoring; - role/task examples; - human-review and fairness rules. - Stage 3: - visible managed-device agent; - signed policy; - work/task session state; - encrypted local journal; - adapter SDK boundary; - device identity, update and security controls. - Stage 4: - signed at-least-once ingestion with application idempotency; - schema governance; - Kafka-compatible topics; - PostgreSQL evidence metadata; - encrypted object storage; - deterministic replay; - telemetry gaps; - retention, access and audit. - Stage 5: - application/window/process evidence; - event-driven visual states; - keyboard/mouse metadata; - approved text deltas; - accessibility/UI evidence; - file/browser/shell/Git/build/test evidence contracts; - secure-field suppression; - context-aware idle/automation states; - employee-visible evidence and correction hooks. Java/Spring Boot owns durable domain state, task-assurance workflows, APIs, policy integration and review state. Python owns AI/multimodal interpretation, episode segmentation, task-alignment models, evaluator recommendations and evaluation harnesses. Existing HumanOS task/project, workflow, policy, audit, notification, Model Gateway and event services must be reused. </authoritative_context> <non_negotiable_rules> - Official semantic/tool events and authoritative artefacts outrank visual or AI inference. - Prompt count, tool-call count, token usage, code volume, click count and time online are not productivity or capability scores. - A single AI prompt, task failure or task success cannot establish permanent capability or misconduct. - Every provenance edge and task-assurance finding must include evidence references, source type, confidence, version and missing-evidence indicators. - Actor classifications are HUMAN, AI_AGENT, AUTOMATION, SYSTEM, MIXED or UNKNOWN; UNKNOWN is valid and must not be forced into another class. - Missing sensors or telemetry gaps reduce confidence and cannot be treated as inactivity. - Task Assurance requires an approved Task Execution Contract and evaluates outcomes/criteria, not one preferred working method. - Multiple valid execution methods, accessibility accommodations, research, review, meetings and automated waits must remain representable. - Raw prompts, text, screenshots and source code must not be copied into operational traces or generic logs. - AI evaluators cannot directly create dismissal, discipline, pay, promotion, probation or equivalent employment decisions. - Employees must be able to inspect material evidence, correct task/context attribution, challenge findings and request meaningful human review. </non_negotiable_rules> <stage_6_required_workstreams> 1. Define the Adapter Hub architecture: - adapter lifecycle; - capability manifest; - versioning; - policy permissions; - local/cloud boundary; - health and telemetry gaps; - signing and allowlisting; - conformance tests; - provider-version drift. 2. Define a canonical semantic event model for: - session start/stop; - command start/completion; - prompt submission; - tool start/completion; - permission request/decision; - file/document change; - Git branch/diff/commit/PR; - test/build/CI lifecycle; - IDE diagnostic/debug state; - browser navigation/task context; - simulator/emulator/deployment result; - human review/accept/reject; - generated artefacts; - adapter gaps and unsupported features. 3. Design and specify adapters for: - Chrome/Edge browser; - PowerShell, bash and zsh; - Git CLI and approved repository roots; - GitHub PR/check/review events; - CI/CD and test/build systems; - VS Code-family IDEs; - JetBrains IDEs; - Xcode; - Android Studio/Flutter toolchain; - Docker/container workflows; - Codex CLI/hooks; - Claude Code hooks/session events; - provider-neutral future AI agents. 4. Define AI-agent evidence: - user prompt reference; - system/skill/config version; - plan; - tool calls; - permissions; - generated changes; - commands/processes; - tests; - human review; - accepted/rejected changes; - stop/result; - model/provider/version; - cost/latency as operational data only. 5. Define adapter security/privacy controls: - secret scanning; - content references rather than generic logs; - least privilege; - signed adapter manifests; - provider-specific permission scopes; - task/session/policy enforcement; - redaction; - local suppression; - employee visibility. 6. Define adapter coverage and conformance: - supported versions; - required events; - optional events; - unsupported state; - coverage score; - telemetry gaps; - upgrade tests; - contract compatibility; - fallback to Stage 5 universal evidence. 7. Produce Stage 6 APIs/events, backlog, tests, risks, ADRs, gate and sources. </stage_6_required_workstreams> <stage_7_required_workstreams> 1. Define the Provenance Graph: - Actor; - HumanInput; - AgentSession; - AgentPrompt; - ToolCall; - ProcessExecution; - FileChange; - TextDelta; - VisualState; - Artefact; - ReviewAction; - TaskContract; - AcceptanceCriterion; - QualityGate; - WorkEpisode; - TaskAssessment; - Blocker; - Correction; - ReviewDecision. 2. Define canonical provenance relationships: - initiated; - prompted; - invoked; - generated; - modified; - formatted; - tested; - reviewed; - accepted; - rejected; - caused; - correlated_with; - superseded; - satisfied; - contradicted; - blocked_by; - corrected_by. 3. Define correlation rules: - temporal windows; - device/session/task scope; - process parent/child; - agent/tool correlation IDs; - file hash/diff; - command/process result; - text-delta/input correlation; - visual-state transitions; - Git/PR/CI links; - ambiguity handling; - evidence hierarchy; - confidence calibration. 4. Define Work Episode segmentation: - task-focused work; - supporting research; - code/document review; - AI-agent direction; - AI-agent execution; - automated execution wait; - collaboration; - learning; - blocked; - idle unexplained; - possibly unrelated; - private/excluded; - insufficient evidence. 5. Define task alignment: - ON_TASK; - SUPPORTING_TASK; - OTHER_ASSIGNED_TASK; - BLOCKED; - AUTOMATED_EXECUTION; - AUTOMATED_EXECUTION_WAIT; - LEARNING; - COLLABORATION; - POSSIBLY_UNRELATED; - UNASSIGNED_WORK; - PRIVATE_OR_EXCLUDED; - INSUFFICIENT_EVIDENCE. 6. Define the Task Assurance Engine: - compile active Task Execution Contract; - evaluate acceptance criteria; - evaluate quality gates; - detect missing evidence; - detect rework and scope expansion; - detect blockers/environment failures; - distinguish employee claim from verified completion; - maintain criterion state; - create completion recommendation; - route reviewer decisions; - preserve employee response and correction. 7. Separate deterministic evaluators from AI-assisted evaluators: - deterministic: - test/build result; - Git/PR state; - artefact existence/hash; - policy/quality gate; - required review; - deadline/state; - secure scan result; - telemetry completeness. - AI-assisted: - episode boundaries; - task relevance; - root-cause narrative; - work-method quality; - blocker type; - evidence sufficiency recommendation; - coaching recommendation. - human-reviewed: - material negative finding; - completion dispute; - high-impact quality/capability inference; - consequential employment use. 8. Define confidence and completeness: - evidence reliability; - coverage; - telemetry gaps; - contradictory evidence; - alternative explanation; - task-contract quality; - model calibration; - reviewer agreement; - correction/overturn rate. 9. Build an evaluation dataset: - positive task completions; - partial completion; - unsupported completion claim; - valid alternate method; - environmental blocker; - unclear requirement; - AI-agent overreach; - good AI supervision; - automated wait; - legitimate reading/review; - accessibility accommodation; - unrelated activity; - missing telemetry; - false idle; - conflicting evidence; - employee correction. 10. Define human review and employee challenge: - material finding package; - evidence links; - model/rule version; - employee explanation; - reviewer rationale; - decision; - override; - audit; - appeal; - SLA; - assessment revision. 11. Define Stage 7 APIs/events, backlog, tests, risks, ADRs, gate and sources. </stage_7_required_workstreams> <architecture_constraints> - Reuse Stage 3 Adapter SDK and Stage 4/5 event contracts. - Provider-specific adapters sit behind a provider-neutral Adapter Hub contract. - Java/Spring services own durable adapter registry, task-assessment state, criteria state, review workflow and public APIs. - Python services/workers produce versioned evaluator recommendations and cannot directly write final high-impact states. - Use PostgreSQL relational provenance initially; introduce a dedicated graph database only after Stage 7 query benchmarks justify it. - Use Kafka-compatible event streams and CloudEvents-style envelopes. - Use OpenTelemetry for operational agent/service telemetry only; sensitive evidence remains in the Evidence domain. - Every adapter and evaluator has a version, owner, capability declaration, test suite and rollback path. </architecture_constraints> <output_contract> Update the existing workbook using one combined Stage 6–7 package with dedicated sheets for: 1. Stage 6-7 Dashboard 2. Semantic Adapter Architecture 3. Adapter SDK Contract 4. Provider Event Matrix 5. Browser Adapter 6. Shell and Process Adapter 7. Git CI and IDE Adapters 8. AI Agent Adapter Hub 9. Adapter Conformance Tests 10. Provenance Graph Model 11. Provenance Relationship Rules 12. Correlation Engine 13. Work Episode Model 14. Task Alignment Model 15. Acceptance Criteria Engine 16. Quality and Blocker Model 17. Evaluator Architecture 18. Evaluation Dataset 19. Human Review and Correction 20. Stage 6-7 APIs and Events 21. Stage 6 Backlog 22. Stage 7 Backlog 23. Stage 6-7 Risks 24. Stage 6-7 ADRs 25. Stage 6 Gate 26. Stage 7 Gate 27. Stage 6-7 Sources Every implementation/backlog row must include: - unique ID; - owner; - contributors; - dependencies; - priority; - effort; - deliverable; - acceptance criteria; - test requirement; - privacy/security impact; - status. Every inference/evaluator row must distinguish: - fact; - deterministic derivation; - AI inference; - assumption; - unresolved question; - human decision. Use formulas for readiness, completion, risk and evaluation coverage. </output_contract> <validation> Before completion, validate that: 1. Provider/tool events normalise without losing source/provider/version lineage. 2. Adapters cannot bypass device policy, secure-field suppression, evidence classification or audit. 3. Official semantic events override conflicting visual inference. 4. Human, AI-agent, automation, system, mixed and unknown origins remain representable. 5. Every provenance edge has evidence, confidence and version. 6. Every work episode preserves missing evidence and alternative classifications. 7. Every task assessment traces to an approved Task Execution Contract. 8. Every acceptance criterion traces to deterministic evidence, AI recommendation or human review state. 9. Valid alternate work methods are not penalised. 10. Environmental blockers, accessibility accommodations, reading, review and automated waits do not create false negative findings. 11. No task/quality finding automatically becomes an employment decision. 12. Employees can inspect, correct and challenge material findings. 13. Stage 6 and Stage 7 have separate formal gates even though they are executed under one prompt. 14. The workbook passes formula, source, consistency and visual-quality checks. </validation>
A136: Combined Next Execution Prompt — Stages 8 and 9
A137: <identity> You are one integrated senior delivery team comprising: - product architects and HR/L&D leaders; - organisational psychologists and capability-framework specialists; - Java/Spring Boot domain architects; - Python/AI scoring, evaluation and recommendation engineers; - knowledge-graph, data and analytics engineers; - governance, DPO, legal, security and employee-experience representatives; - software engineering, QA, DevOps and future-vertical domain experts. Work as one team. Execute Stage 8 and Stage 9 as a combined Capability Development & Growth Coach workstream, while preserving a separate Stage 8 Capability Graph gate and Stage 9 Coaching/Learning gate. </identity> <mission> Execute Stages 8 and 9 of Nessovo HumanOS Work Intelligence. Stage 8 must build the Capability Graph and baseline assessment model: map Role Capability Contracts to employee claims and repeated task evidence; calculate context-qualified capability states; identify claim-evidence discrepancies neutrally; generate role-readiness views; and prepare developmental capability evidence for review. Stage 9 must build the Growth Coach and learning loop: convert task, blocker and capability evidence into employee-facing observe/nudge/assist/teach/escalate interventions; assign learning actions; track whether training is applied in later work; measure coaching effectiveness; and prepare safe manager/L&D summaries. Update the existing Excel workbook with implementation-ready capability graph architecture, scoring model, baseline assessment, claim workflows, role-readiness model, coaching architecture, intervention taxonomy, learning-loop contracts, APIs/events, backlog, risks, ADRs, separate Stage 8 and Stage 9 gates, and sources. </mission> <authoritative_context> Existing foundations in the workbook: - Stage 2 provides: - Role Capability Contract; - Task Execution Contract; - capability levels 0–5; - evidence scoring; - claim-evidence discrepancy rules; - role and task templates; - fairness and human-review guardrails. - Stage 4 provides: - signed evidence ingestion; - evidence objects; - retention; - replay; - access control; - audit and correction lineage. - Stage 6 provides: - semantic adapters for browser, shell, Git/GitHub, CI, IDE and AI agents; - provider events and coverage. - Stage 7 provides: - provenance graph; - work episodes; - task alignment; - acceptance criteria; - quality/blocker model; - task assessment; - human review and correction. Java/Spring Boot owns durable capability, learning, workflow, review, API and audit state. Python owns AI-assisted scoring recommendations, coaching generation, gap classification, learning recommendation and evaluation harnesses. Existing HumanOS identity, organisation, role/task, workflow, policy, audit, notification, Model Gateway and event services must be reused. </authoritative_context> <non_negotiable_rules> - A job description, CV, interview answer or self-assessment is a claim or requirement, not proof. - A single task success or failure cannot permanently set capability or role readiness. - Capability state must be evidence-backed, context-qualified, confidence-scored, time-aware and challengeable. - Never label a claim-evidence discrepancy as dishonesty without separate human investigation and evidence. - Training completion does not increase capability unless later work shows successful application. - Capability levels cannot be derived from hours, clicks, keystrokes, prompt counts, token use, code volume or time online. - Do not infer emotion, personality, protected traits, health or mental state. - Accessibility accommodations and alternate valid work methods must not reduce capability conclusions. - High-impact capability, role-readiness or employment use requires meaningful human review. - Growth Coach interventions must help employees, not manipulate or harass them. - Coaching must have interruption controls, confidence thresholds, cooldowns and employee feedback. - Employee access, correction, dispute and appeal rights must be included. </non_negotiable_rules> <stage_8_required_workstreams> 1. Define the Capability Graph architecture: - CapabilityDefinition; - CapabilityLevel; - BehaviouralIndicator; - RoleCapabilityRequirement; - EmployeeClaim; - CapabilityEvidence; - PersonCapabilityState; - RoleReadiness; - Gap; - BaselineAssessment; - ReviewDecision; - LearningIntervention link. 2. Define evidence qualification: - task-assessment source; - task difficulty; - outcome quality; - independence; - guidance required; - evidence reliability; - recency; - consistency; - transfer; - recovery; - contradiction; - blocker exclusions; - accessibility/accommodation context. 3. Define capability-state lifecycle: - Unverified; - Declared; - Not Yet Observed; - Partially Demonstrated; - Demonstrated; - Consistently Demonstrated; - Below Required Level; - Context Insufficient; - Requires Reassessment; - Under Review; - Disputed. 4. Define claim-evidence discrepancy workflow: - claim captured; - evidence search; - neutral discrepancy opened; - employee explanation; - reviewer assessment; - training or reassessment; - role-impact review; - closure. 5. Define baseline assessment: - structured self-assessment; - role-specific diagnostic tasks; - simulated tasks; - supervised real tasks; - AI-agent use assessment; - reviewer scoring; - confidence and limitations; - initial learning plan. 6. Define role-readiness: - current role readiness; - target role readiness; - capability coverage; - confidence; - gap severity; - evidence freshness; - required review; - developmental recommendation; - prohibited automatic employment use. 7. Define Stage 8 APIs/events, backlog, tests, risks, ADRs, gate and sources. </stage_8_required_workstreams> <stage_9_required_workstreams> 1. Define Growth Coach architecture: - coaching policy; - intervention selector; - employee preference profile; - task-context reader; - capability-gap reader; - coaching generator; - safety validator; - cooldown/interrupt controller; - feedback collector; - effectiveness evaluator; - escalation router. 2. Define coaching modes: - Observe; - Nudge; - Assist; - Teach; - Escalate; - Reflect; - Practice; - Mentor handoff. 3. Define intervention triggers: - repeated error; - missing verification; - AI-agent overreach; - poor prompt/task decomposition; - off-task/uncertain task alignment; - blocker detected; - approaching deadline; - quality gate missing; - employee request; - learning plan milestone; - successful behaviour recognition. 4. Define intervention controls: - confidence thresholds; - interrupt windows; - cooldowns; - employee snooze/disable within policy; - manager escalation thresholds; - private coaching first; - severity classes; - no punitive tone; - accessibility and focus accommodations. 5. Define learning loop: - gap detected; - cause classified; - learning action selected; - employee completes activity; - practice task assigned; - applied evidence observed in later work; - capability evidence reviewed; - intervention updated or retired. 6. Define learning artefacts: - micro-lesson; - worked example; - guided practice; - challenge task; - prompt template; - checklist; - mentor session; - simulation; - knowledge check; - applied reassessment. 7. Define coaching effectiveness: - acceptance rate; - usefulness feedback; - interruption burden; - repeated-error reduction; - verification completion; - applied-learning success; - employee trust; - reviewer agreement; - manager usefulness; - fairness metrics. 8. Define safe manager/L&D reporting: - development summary; - gap themes; - training progress; - applied improvement; - support needed; - unresolved blockers; - employee response; - no raw private coaching messages by default. 9. Define Stage 9 APIs/events, backlog, tests, risks, ADRs, gate and sources. </stage_9_required_workstreams> <architecture_constraints> - Java/Spring services own capability state, learning state, workflow state and APIs. - Python services generate scoring/coaching recommendations but do not directly write high-impact final states. - Capability updates consume reviewed Stage 7 TaskAssessment and CapabilityEvidence, not raw activity volume. - Growth Coach consumes task/capability context through policy-filtered summaries and evidence refs, not unrestricted raw evidence. - All interventions are versioned, auditable and feedback-linked. - Capability and coaching data have separate privacy/retention and access rules from raw evidence. - Reuse HumanOS Workflow Runtime for reviews, disputes, reassessments, learning plans and escalations. - Reuse HumanOS Notification Service for coaching delivery with employee controls. - Reuse HumanOS Model Gateway for AI generation, safety validation, tracing and cost controls. </architecture_constraints> <output_contract> Update the existing workbook using one combined Stage 8–9 package with dedicated sheets for: 1. Stage 8-9 Dashboard 2. Capability Graph Architecture 3. Capability Evidence Model 4. Capability Scoring Model 5. Claim Discrepancy Workflow 6. Baseline Assessment Model 7. Role Readiness Model 8. Capability Review and Audit 9. Growth Coach Architecture 10. Coaching Modes and Triggers 11. Intervention Policy 12. Learning Loop Model 13. Learning Artefacts 14. Coaching Effectiveness Metrics 15. Manager and L&D Reporting 16. Stage 8-9 APIs and Events 17. Stage 8 Backlog 18. Stage 9 Backlog 19. Stage 8-9 Risks 20. Stage 8-9 ADRs 21. Stage 8 Gate 22. Stage 9 Gate 23. Stage 8-9 Sources Every implementation/backlog row must include: - unique ID; - owner; - contributors; - dependencies; - priority; - effort; - deliverable; - acceptance criteria; - test requirement; - privacy/security impact; - status. Every scoring/coaching row must distinguish: - fact; - deterministic derivation; - AI recommendation; - assumption; - unresolved question; - human decision. Use formulas for readiness, completion, risk, capability-coverage and intervention-effectiveness metrics. </output_contract> <validation> Before completion, validate that: 1. Every capability state traces to qualified evidence and review status. 2. Role readiness cannot be calculated from claims alone. 3. Single-task evidence cannot permanently set capability. 4. Claim discrepancies remain neutral and reviewable. 5. Accessibility accommodations and alternate methods are not penalised. 6. Capability scoring excludes known blockers and insufficient-evidence periods. 7. Training completion alone does not improve capability level. 8. Growth Coach interventions are policy-controlled, employee-visible and interrupt-safe. 9. Coaching recommendations are evidence-linked and challengeable. 10. Manager/L&D reports do not expose raw private coaching messages by default. 11. Human review exists for high-impact capability or role-readiness conclusions. 12. Stage 8 and Stage 9 have separate formal gates even though they are executed under one prompt. 13. The workbook passes formula, source, consistency and visual-quality checks. </validation>
... A261: Repository Rapidtackltd/humanos-backend-services was assessed at commit 79a38ade1fc0163cadf39ae3cccd466b7f8d5d9d. The existing ai-execution-service is retained, but Stage 12A cannot proceed to model qualification or pilot until P0 remediation closes the single-door cutover, central subscription-CLI defaults, contract/registry/routing/qualification gaps, credential fallback, raw prompt/output persistence, endpoint broker and development-review workflow.

Sheet Foundation Dashboard
A1: Foundation Dashboard — Stage 0 and Stage 1
A2: Current state: research and draft artefacts are complete; formal Nessovo ownership, legal/DPO, worker, security, architecture and budget approvals remain outstanding.
A4: Foundation KPI | B4: Current value
A5: Combined workplan maturity | B5: =AVERAGE('Stage 0-1 Workplan'!K5:K71) -> 0.68208955
A6: Stage 0 workplan maturity | B6: =AVERAGEIF('Stage 0-1 Workplan'!B5:B71,0,'Stage 0-1 Workplan'!K5:K71) -> 0.65294118
A7: Stage 1 workplan maturity | B7: =AVERAGEIF('Stage 0-1 Workplan'!B5:B71,1,'Stage 0-1 Workplan'!K5:K71) -> 0.71212121
A8: Stage 0 gate readiness | B8: ='Stage 0-1 Gates'!O6 -> 0.57222222
A9: Stage 1 gate readiness | B9: ='Stage 0-1 Gates'!O7 -> 0.56666667
A10: Mandatory items not started/blocked | B10: ='Stage 0-1 Gates'!O8 -> 5
A11: Critical/high tasks below draft-ready | B11: =COUNTIFS('Stage 0-1 Workplan'!I5:I71,"Critical",'Stage 0-1 Workplan'!K5:K71,"<0.8")+COUNTIFS('Stage 0-1 Workplan'!I5:I71,"High",'Stage 0-1 Workplan'!K5:K71,"<0.8") -> 16
A12: Residual high/critical threats | B12: =COUNTIF('Foundation Threats'!K5:K34,">=15") -> 0
A13: ADRs accepted in principle/accepted | B13: =COUNTIF('Architecture Decisions'!C5:C26,"Accepted in principle")+COUNTIF('Architecture Decisions'!C5:C26,"Accepted") -> 20
A14: Registered research sources | B14: =COUNTA('Source Register'!A5:A200) -> 164
A17: Stage | B17: Maturity %
A18: Stage 0 workplan | B18: =B6*100 -> 65.294118 | D18: Executive decision state
A19: Stage 1 workplan | B19: =B7*100 -> 71.212121 | D19: Item | E19: Current state
A20: Combined foundation | B20: =B5*100 -> 68.208955 | D20: Stage 0 foundation content | E20: Draft package complete
D21: Stage 0 organisational approval | E21: Pending legal/DPO/worker/security/leadership review
D22: Stage 1 research and architecture content | E22: Draft package complete
D23: Stage 1 organisational approval | E23: Pending architecture/licence/cost/resource review
D24: Entry to Stages 2 and 3 | E24: Prompt-ready; gate approval still required
A27: Immediate Nessovo decisions required before formal gate approval
A28: Priority | B28: Decision | C28: Decision authority | D28: Why now | E28: Required evidence | F28: Current status
A29: 1 | B29: Name executive sponsor, product owner and programme lead. | C29: CEO/CTO | D29: No foundation gate can be accountable without named owners. | E29: Named RACI. | F29: Owner Input
A30: 2 | B30: Commission UK and Pakistan/Lahore legal reviews and independent DPO advice. | C30: CEO/Legal/DPO | D30: Keystroke/screenshot/performance monitoring is high risk and jurisdiction-specific. | E30: Legal memoranda and DPIA. | F30: Owner Input
A31: 3 | B31: Approve worker consultation approach and participant-protection rules. | C31: HR/DPO/Executive Sponsor | D31: Worker voice is required before the pilot design is frozen. | E31: Consultation plan and record. | F31: Draft Ready
A32: 4 | B32: Confirm current HumanOS Java/Spring and foundation-service inventory. | C32: CTO/Enterprise Architect | D32: Technology and service boundaries depend on actual platform capability. | E32: Platform inventory. | F32: Open
A33: 5 | B33: Approve proprietary-core versus commodity build/buy strategy. | C33: CTO/Product/Legal | D33: Stage 3 implementation and licences depend on this boundary. | E33: Build/Buy matrix and licence review. | F33: Draft Ready
A34: 6 | B34: Approve reference architecture and initial deployment boundaries. | C34: Architecture Board | D34: Avoid duplicated HumanOS services and premature nano-services. | E34: ADRs and architecture map. | F34: In Review
A35: 7 | B35: Provide pilot sizing, device, location, tool and retention assumptions. | C35: Product/HR/IT/DPO | D35: Cost, architecture and test planning require realistic inputs. | E35: Resolved assumptions register. | F35: Open
A36: 8 | B36: Commit Stage 2–3 team, devices, security review and budget. | C36: CEO/CTO/CFO | D36: The next stages require cross-functional capacity, not engineering alone. | E36: Resource plan. | F36: Owner Input
A40: Foundation package delivered in this workbook
A41: Deliverable | B41: Sheet | C41: State
A42: Master prompt and next-stage prompts | B42: Master Prompts | C42: Complete
A43: Detailed action plan | B43: Stage 0-1 Workplan | C43: Complete
A44: Product charter | B44: Product Charter v1 | C44: Draft complete
A45: Purpose and data policy | B45: Purpose Policy Matrix | C45: Draft complete
A46: Stakeholder accountability | B46: Stakeholder RACI | C46: Role-level draft
A47: Market and OSS evidence | B47: Market Landscape / GitHub OSS Scan | C47: Research complete
A48: Build/buy decisions | B48: Build Buy Decisions | C48: Draft complete
A49: HumanOS architecture | B49: Reference Architecture / Architecture Decisions | C49: Draft complete
A50: Approval gates | B50: Stage 0-1 Gates | C50: Criteria complete; approvals pending
A51: Assumptions, threats and pilot | B51: Assumptions Questions / Foundation Threats / Pilot Definition | C51: Draft complete

Sheet Stage 0-1 Workplan
A1: Stage 0–1 Foundation Workplan
A2: Combined Foundation & Validation workstream. Draft deliverables are complete where marked; real legal, worker, security and leadership approvals remain pending until Nessovo records them.
A4: ID | B4: Stage | C4: Workstream | D4: Task / Decision | E4: Description | F4: Accountable owner | G4: Contributors | H4: Dependencies | I4: Priority | J4: Status | K4: Completion weight | L4: Effort days | M4: Deliverable | N4: Acceptance criteria | O4: Evidence / source | P4: Gate | Q4: Target week | R4: Notes
A5: FND-001 | B5: 0 | C5: Programme governance | D5: Confirm naming and product identity | E5: Use Nessovo as the company name and HumanOS Work Intelligence as the working module name. | F5: CEO/CTO | G5: Product | H5: None | I5: Critical | J5: Completed | K5: =IF(J5="Completed",1,IF(J5="Draft Complete",0.8,IF(J5="In Review",0.6,IF(J5="Requires Owner Input",0.3,IF(J5="Blocked",0.1,IF(J5="Deferred",0.2,0)))))) -> 1 | L5: 0.5 | M5: Canonical naming decision | N5: All foundation artefacts use Nessovo and no obsolete company name. | O5: User instruction | P5: Stage 0 Gate | Q5: W1 | R5: Completed in workbook.
A6: FND-002 | B6: 0 | C6: Programme governance | D6: Appoint executive sponsor | E6: Name the executive accountable for purpose, risk appetite and final foundation approvals. | F6: CEO | G6: Board/CTO | H6: FND-001 | I6: Critical | J6: Requires Owner Input | K6: =IF(J6="Completed",1,IF(J6="Draft Complete",0.8,IF(J6="In Review",0.6,IF(J6="Requires Owner Input",0.3,IF(J6="Blocked",0.1,IF(J6="Deferred",0.2,0)))))) -> 0.3 | L6: 0.5 | M6: Sponsor appointment | N6: Named individual and authority recorded. | O6: Internal decision | P6: Stage 0 Gate | Q6: W1
A7: FND-003 | B7: 0 | C7: Programme governance | D7: Appoint product owner and programme lead | E7: Assign accountable owners for product decisions and integrated delivery. | F7: CEO/CTO | G7: Product/PMO | H7: FND-002 | I7: Critical | J7: Requires Owner Input | K7: =IF(J7="Completed",1,IF(J7="Draft Complete",0.8,IF(J7="In Review",0.6,IF(J7="Requires Owner Input",0.3,IF(J7="Blocked",0.1,IF(J7="Deferred",0.2,0)))))) -> 0.3 | L7: 1 | M7: Named ownership | N7: Product owner, programme lead and deputies recorded. | O7: Internal decision | P7: Stage 0 Gate | Q7: W1
A8: FND-004 | B8: 0 | C8: Product strategy | D8: Approve Product Charter v1 draft | E8: Define the problem, vision, mission, value, scope, non-scope and strategic fit within HumanOS. | F8: Product Owner | G8: CEO/CTO/Architecture/HR | H8: FND-001 | I8: Critical | J8: Draft Complete | K8: =IF(J8="Completed",1,IF(J8="Draft Complete",0.8,IF(J8="In Review",0.6,IF(J8="Requires Owner Input",0.3,IF(J8="Blocked",0.1,IF(J8="Deferred",0.2,0)))))) -> 0.8 | L8: 2 | M8: Product Charter v1 | N8: Charter contains purpose, beneficiaries, differentiation, principles, scope and kill criteria. | O8: Product Charter v1 sheet | P8: Stage 0 Gate | Q8: W1 | R8: Leadership approval pending.
A9: FND-005 | B9: 0 | C9: Product strategy | D9: Confirm market positioning | E9: Position as task execution assurance, capability development and human–AI work intelligence rather than surveillance software. | F9: CEO/Product | G9: Marketing/Legal/Employee Rep | H9: FND-004 | I9: Critical | J9: Draft Complete | K9: =IF(J9="Completed",1,IF(J9="Draft Complete",0.8,IF(J9="In Review",0.6,IF(J9="Requires Owner Input",0.3,IF(J9="Blocked",0.1,IF(J9="Deferred",0.2,0)))))) -> 0.8 | L9: 1 | M9: Positioning statement | N9: Positioning clearly states employee and employer value and avoids activity-volume scoring. | O9: Product Charter v1 / market research | P9: Stage 0 Gate | Q9: W1
A10: FND-006 | B10: 0 | C10: Employee value | D10: Define employee value proposition | E10: Specify how the product protects legitimate work, explains blockers, improves AI use, supports learning and allows correction. | F10: Product/HR | G10: L&D/Employee Rep | H10: FND-004 | I10: High | J10: Draft Complete | K10: =IF(J10="Completed",1,IF(J10="Draft Complete",0.8,IF(J10="In Review",0.6,IF(J10="Requires Owner Input",0.3,IF(J10="Blocked",0.1,IF(J10="Deferred",0.2,0)))))) -> 0.8 | L10: 1.5 | M10: Employee value proposition | N10: At least five measurable employee benefits are defined. | O10: Product Charter v1 | P10: Stage 0 Gate | Q10: W1
A11: FND-007 | B11: 0 | C11: Employer value | D11: Define employer and team-lead value | E11: Specify task assurance, quality, blocker, capability, coaching and organisational-learning outcomes. | F11: Product | G11: Operations/Engineering Leads | H11: FND-004 | I11: High | J11: Draft Complete | K11: =IF(J11="Completed",1,IF(J11="Draft Complete",0.8,IF(J11="In Review",0.6,IF(J11="Requires Owner Input",0.3,IF(J11="Blocked",0.1,IF(J11="Deferred",0.2,0)))))) -> 0.8 | L11: 1 | M11: Employer value proposition | N11: Outcomes are evidence-based and separated from raw monitoring. | O11: Product Charter v1 | P11: Stage 0 Gate | Q11: W1
A12: FND-008 | B12: 0 | C12: Product boundaries | D12: Approve prohibited uses and non-goals | E12: Exclude covert general monitoring, emotion/personality inference, automated employment decisions and activity-volume productivity scores. | F12: Legal/DPO/Product | G12: HR/Security/Employee Rep | H12: FND-004 | I12: Critical | J12: Draft Complete | K12: =IF(J12="Completed",1,IF(J12="Draft Complete",0.8,IF(J12="In Review",0.6,IF(J12="Requires Owner Input",0.3,IF(J12="Blocked",0.1,IF(J12="Deferred",0.2,0)))))) -> 0.8 | L12: 1.5 | M12: Prohibited-use register | N12: All prohibited uses are explicit, testable and enforceable by policy. | O12: Product Charter v1 / Purpose Policy Matrix | P12: Stage 0 Gate | Q12: W1 | R12: Formal legal approval pending.
A13: FND-009 | B13: 0 | C13: Pilot scope | D13: Define initial vertical and pilot cohort | E13: Limit initial pilot to AI-assisted software development on company-managed devices. | F13: Product/CTO | G13: Engineering/HR | H13: FND-004 | I13: Critical | J13: Draft Complete | K13: =IF(J13="Completed",1,IF(J13="Draft Complete",0.8,IF(J13="In Review",0.6,IF(J13="Requires Owner Input",0.3,IF(J13="Blocked",0.1,IF(J13="Deferred",0.2,0)))))) -> 0.8 | L13: 1 | M13: Pilot scope statement | N13: Roles, device types, task classes, exclusions and participant count assumptions are stated. | O13: Pilot Definition sheet | P13: Stage 0 Gate | Q13: W1
A14: FND-010 | B14: 0 | C14: Ontology foundation | D14: Approve foundation terminology | E14: Define fact, inference, recommendation, assumption, task assurance, capability evidence and consequential decision. | F14: Product/Architecture | G14: Legal/AI/HR | H14: FND-004 | I14: High | J14: Draft Complete | K14: =IF(J14="Completed",1,IF(J14="Draft Complete",0.8,IF(J14="In Review",0.6,IF(J14="Requires Owner Input",0.3,IF(J14="Blocked",0.1,IF(J14="Deferred",0.2,0)))))) -> 0.8 | L14: 1 | M14: Canonical glossary | N14: Terms are unambiguous and reused across artefacts. | O14: Master Prompts / Product Charter v1 | P14: Stage 0 Gate | Q14: W1
A15: FND-011 | B15: 0 | C15: Privacy governance | D15: Complete purpose-by-data matrix | E15: Map every proposed data category to purpose, necessity, minimisation, access, retention and prohibited use. | F15: DPO/Product | G15: Security/Architecture/HR | H15: FND-008 | I15: Critical | J15: Draft Complete | K15: =IF(J15="Completed",1,IF(J15="Draft Complete",0.8,IF(J15="In Review",0.6,IF(J15="Requires Owner Input",0.3,IF(J15="Blocked",0.1,IF(J15="Deferred",0.2,0)))))) -> 0.8 | L15: 3 | M15: Purpose Policy Matrix | N15: No data category exists without a defined purpose and minimisation rationale. | O15: Purpose Policy Matrix sheet | P15: Stage 0 Gate | Q15: W1 | R15: DPO validation pending.
A16: FND-012 | B16: 0 | C16: Privacy governance | D16: Assess less intrusive alternatives | E16: For every intrusive capture method, assess whether task artefacts or metadata can achieve the purpose first. | F16: DPO/Product | G16: Architecture/Employee Rep | H16: FND-011 | I16: Critical | J16: Draft Complete | K16: =IF(J16="Completed",1,IF(J16="Draft Complete",0.8,IF(J16="In Review",0.6,IF(J16="Requires Owner Input",0.3,IF(J16="Blocked",0.1,IF(J16="Deferred",0.2,0)))))) -> 0.8 | L16: 2 | M16: Alternatives assessment | N16: Alternatives and residual necessity are documented per data type. | O16: Purpose Policy Matrix sheet | P16: Stage 0 Gate | Q16: W1
A17: FND-013 | B17: 0 | C17: Privacy governance | D17: Complete DPIA screening draft | E17: Document why the intended keystroke/screenshot/performance use is high-risk and requires a full DPIA. | F17: DPO | G17: Legal/Product/Security | H17: FND-011 | I17: Critical | J17: Draft Complete | K17: =IF(J17="Completed",1,IF(J17="Draft Complete",0.8,IF(J17="In Review",0.6,IF(J17="Requires Owner Input",0.3,IF(J17="Blocked",0.1,IF(J17="Deferred",0.2,0)))))) -> 0.8 | L17: 1 | M17: DPIA screening record | N17: High-risk triggers, affected people and initial risks are recorded. | O17: ICO monitoring guidance | P17: Stage 0 Gate | Q17: W1 | R17: Formal DPO advice not yet recorded.
A18: FND-014 | B18: 0 | C18: Privacy governance | D18: Prepare full DPIA input pack | E18: Provide processing description, necessity, risks, safeguards, consultation and residual-risk questions. | F18: DPO | G18: Legal/Security/Product | H18: FND-013 | I18: Critical | J18: Draft Complete | K18: =IF(J18="Completed",1,IF(J18="Draft Complete",0.8,IF(J18="In Review",0.6,IF(J18="Requires Owner Input",0.3,IF(J18="Blocked",0.1,IF(J18="Deferred",0.2,0)))))) -> 0.8 | L18: 3 | M18: DPIA working pack | N18: Pack contains all information needed for an independent DPO/legal assessment. | O18: Governance / Foundation Threats / Purpose Policy Matrix | P18: Stage 0 Gate | Q18: W2
A19: FND-015 | B19: 0 | C19: Privacy governance | D19: Obtain and record DPO advice | E19: Independent DPO reviews the DPIA, safeguards and whether the pilot may proceed. | F19: DPO | G19: Legal/Executive Sponsor | H19: FND-014 | I19: Critical | J19: Not Started | K19: =IF(J19="Completed",1,IF(J19="Draft Complete",0.8,IF(J19="In Review",0.6,IF(J19="Requires Owner Input",0.3,IF(J19="Blocked",0.1,IF(J19="Deferred",0.2,0)))))) -> 0 | L19: 2 | M19: DPO advice record | N19: Advice, conditions, dissent and residual risks are signed and stored. | O19: Independent review required | P19: Stage 0 Gate | Q19: W2
A20: FND-016 | B20: 0 | C20: Legal | D20: UK legal basis and employment-law review | E20: Confirm lawful basis, special-category conditions, interception rules, employment documentation and automated-decision safeguards. | F20: UK Legal Counsel | G20: DPO/HR | H20: FND-014 | I20: Critical | J20: Requires Owner Input | K20: =IF(J20="Completed",1,IF(J20="Draft Complete",0.8,IF(J20="In Review",0.6,IF(J20="Requires Owner Input",0.3,IF(J20="Blocked",0.1,IF(J20="Deferred",0.2,0)))))) -> 0.3 | L20: 3 | M20: UK legal memorandum | N20: Legal counsel identifies permitted pilot scope, conditions and prohibited uses. | O20: UK counsel / ICO / GOV.UK | P20: Stage 0 Gate | Q20: W2 | R20: Not legal advice in this workbook.
A21: FND-017 | B21: 0 | C21: Legal | D21: Pakistan/Lahore legal review scope | E21: Commission a separate employment, privacy, interception and cross-border data review for Lahore operations. | F21: Pakistan Legal Counsel | G21: HR/DPO/Security | H21: FND-014 | I21: Critical | J21: Requires Owner Input | K21: =IF(J21="Completed",1,IF(J21="Draft Complete",0.8,IF(J21="In Review",0.6,IF(J21="Requires Owner Input",0.3,IF(J21="Blocked",0.1,IF(J21="Deferred",0.2,0)))))) -> 0.3 | L21: 3 | M21: Pakistan legal memorandum | N21: Applicable laws, notices, consent/consultation, localisation and transfer requirements are documented. | O21: Local counsel required | P21: Stage 0 Gate | Q21: W2
A22: FND-018 | B22: 0 | C22: Worker voice | D22: Approve worker consultation plan | E22: Define early consultation, representative participation, feedback capture and response commitments. | F22: HR/DPO | G22: Employee Rep/Product | H22: FND-011 | I22: Critical | J22: Draft Complete | K22: =IF(J22="Completed",1,IF(J22="Draft Complete",0.8,IF(J22="In Review",0.6,IF(J22="Requires Owner Input",0.3,IF(J22="Blocked",0.1,IF(J22="Deferred",0.2,0)))))) -> 0.8 | L22: 1.5 | M22: Consultation plan | N22: Participants, timing, topics, confidentiality and decision-response process are defined. | O22: ICO guidance / Pilot Definition | P22: Stage 0 Gate | Q22: W1
A23: FND-019 | B23: 0 | C23: Worker voice | D23: Run and document worker consultation | E23: Consult affected employees or representatives before pilot approval. | F23: HR | G23: DPO/Product/Employee Rep | H23: FND-018 | I23: Critical | J23: Not Started | K23: =IF(J23="Completed",1,IF(J23="Draft Complete",0.8,IF(J23="In Review",0.6,IF(J23="Requires Owner Input",0.3,IF(J23="Blocked",0.1,IF(J23="Deferred",0.2,0)))))) -> 0 | L23: 3 | M23: Consultation record | N23: Views, objections, changes accepted/rejected and reasons are documented. | O23: Consultation evidence | P23: Stage 0 Gate | Q23: W2
A24: FND-020 | B24: 0 | C24: Transparency | D24: Draft worker privacy notice | E24: Explain what is captured, why, when, who sees it, retention, rights, dispute and contact routes. | F24: DPO/Legal | G24: HR/Product | H24: FND-011 | I24: Critical | J24: Draft Complete | K24: =IF(J24="Completed",1,IF(J24="Draft Complete",0.8,IF(J24="In Review",0.6,IF(J24="Requires Owner Input",0.3,IF(J24="Blocked",0.1,IF(J24="Deferred",0.2,0)))))) -> 0.8 | L24: 2 | M24: Privacy notice outline | N24: Notice is clear, accessible, task-specific and consistent with policy. | O24: Governance sheet | P24: Stage 0 Gate | Q24: W2 | R24: Legal review pending.
A25: FND-021 | B25: 0 | C25: Transparency | D25: Draft workplace monitoring policy | E25: Define scope, working hours, personal use, exclusions, manager access, prohibited uses and consequences of misuse. | F25: HR/Legal | G25: DPO/Security/Product | H25: FND-020 | I25: Critical | J25: Draft Complete | K25: =IF(J25="Completed",1,IF(J25="Draft Complete",0.8,IF(J25="In Review",0.6,IF(J25="Requires Owner Input",0.3,IF(J25="Blocked",0.1,IF(J25="Deferred",0.2,0)))))) -> 0.8 | L25: 2 | M25: Monitoring policy outline | N25: Policy is consistent with charter, purpose matrix and employee notice. | O25: Governance sheet | P25: Stage 0 Gate | Q25: W2
A26: FND-022 | B26: 0 | C26: Employee rights | D26: Define access, correction and dispute workflow | E26: Employees can view evidence, correct task attribution, explain context and request human review. | F26: Governance Product Owner | G26: DPO/HR/Workflow Team | H26: FND-011 | I26: Critical | J26: Draft Complete | K26: =IF(J26="Completed",1,IF(J26="Draft Complete",0.8,IF(J26="In Review",0.6,IF(J26="Requires Owner Input",0.3,IF(J26="Blocked",0.1,IF(J26="Deferred",0.2,0)))))) -> 0.8 | L26: 2 | M26: Rights workflow | N26: States, deadlines, evidence preservation and reviewer authority are defined. | O26: Governance / Reference Architecture | P26: Stage 0 Gate | Q26: W2
A27: FND-023 | B27: 0 | C27: Human review | D27: Define meaningful human-review standard | E27: Reviewers must understand evidence, consider context and have authority to reject AI recommendations. | F27: HR/Legal/DPO | G27: Domain Experts/Product | H27: FND-022 | I27: Critical | J27: Draft Complete | K27: =IF(J27="Completed",1,IF(J27="Draft Complete",0.8,IF(J27="In Review",0.6,IF(J27="Requires Owner Input",0.3,IF(J27="Blocked",0.1,IF(J27="Deferred",0.2,0)))))) -> 0.8 | L27: 1.5 | M27: Human-review standard | N27: Reviewer qualifications, independence, reasoned decisions and override logging are defined. | O27: ICO human-review guidance | P27: Stage 0 Gate | Q27: W2
A28: FND-024 | B28: 0 | C28: Access governance | D28: Define raw evidence access model | E28: Restrict screenshots/text/keystrokes by role, purpose code, task scope, time and audit. | F28: Security/DPO | G28: IAM/Audit/Product | H28: FND-011 | I28: Critical | J28: Draft Complete | K28: =IF(J28="Completed",1,IF(J28="Draft Complete",0.8,IF(J28="In Review",0.6,IF(J28="Requires Owner Input",0.3,IF(J28="Blocked",0.1,IF(J28="Deferred",0.2,0)))))) -> 0.8 | L28: 2 | M28: Evidence access policy | N28: No default raw-content access; all access is purpose-limited and logged. | O28: Purpose Policy Matrix / Reference Architecture | P28: Stage 0 Gate | Q28: W2
A29: FND-025 | B29: 0 | C29: Data governance | D29: Define retention and deletion principles | E29: Set short raw-evidence retention, longer derived-evidence retention and legal-hold controls. | F29: DPO/Data Governance | G29: Security/Product | H29: FND-011 | I29: Critical | J29: Draft Complete | K29: =IF(J29="Completed",1,IF(J29="Draft Complete",0.8,IF(J29="In Review",0.6,IF(J29="Requires Owner Input",0.3,IF(J29="Blocked",0.1,IF(J29="Deferred",0.2,0)))))) -> 0.8 | L29: 1.5 | M29: Retention schedule draft | N29: Retention is purpose-based, configurable, auditable and supports deletion. | O29: Purpose Policy Matrix | P29: Stage 0 Gate | Q29: W2
A30: FND-026 | B30: 0 | C30: Privacy engineering | D30: Define secure-field and exclusion requirements | E30: Block passwords, authentication codes, known secure controls, private apps/domains and out-of-hours capture. | F30: Security/Desktop Lead | G30: DPO/Product/QA | H30: FND-011 | I30: Critical | J30: Draft Complete | K30: =IF(J30="Completed",1,IF(J30="Draft Complete",0.8,IF(J30="In Review",0.6,IF(J30="Requires Owner Input",0.3,IF(J30="Blocked",0.1,IF(J30="Deferred",0.2,0)))))) -> 0.8 | L30: 2 | M30: Capture exclusion specification | N30: Requirements are testable and designated as pilot blocking controls. | O30: Purpose Policy Matrix / Foundation Threats | P30: Stage 0 Gate | Q30: W2
A31: FND-027 | B31: 0 | C31: Audit | D31: Define purpose codes and immutable access audit | E31: Every evidence access, AI assessment, review, policy change and skill change must record who, why and what. | F31: Audit/Security | G31: DPO/Platform | H31: FND-024 | I31: High | J31: Draft Complete | K31: =IF(J31="Completed",1,IF(J31="Draft Complete",0.8,IF(J31="In Review",0.6,IF(J31="Requires Owner Input",0.3,IF(J31="Blocked",0.1,IF(J31="Deferred",0.2,0)))))) -> 0.8 | L31: 1.5 | M31: Audit event specification | N31: Required audit events and retention are enumerated. | O31: Reference Architecture | P31: Stage 0 Gate | Q31: W2
A32: FND-028 | B32: 0 | C32: Incident response | D32: Define privacy/security incident path | E32: Specify containment, evidence preservation, employee notification, breach assessment and agent-disable path. | F32: CISO/DPO | G32: Platform/HR/Legal | H32: FND-026 | I32: Critical | J32: Draft Complete | K32: =IF(J32="Completed",1,IF(J32="Draft Complete",0.8,IF(J32="In Review",0.6,IF(J32="Requires Owner Input",0.3,IF(J32="Blocked",0.1,IF(J32="Deferred",0.2,0)))))) -> 0.8 | L32: 2 | M32: Incident playbook outline | N32: Named escalation, stop switch and notification responsibilities are defined. | O32: Foundation Threats | P32: Stage 0 Gate | Q32: W2
A33: FND-029 | B33: 0 | C33: Programme governance | D33: Approve stop/hold criteria | E33: Define conditions that automatically hold the pilot, including secret capture, high false-classification, excessive overhead or legal uncertainty. | F33: Executive Sponsor | G33: DPO/CISO/Product/Employee Rep | H33: FND-014 | I33: Critical | J33: Draft Complete | K33: =IF(J33="Completed",1,IF(J33="Draft Complete",0.8,IF(J33="In Review",0.6,IF(J33="Requires Owner Input",0.3,IF(J33="Blocked",0.1,IF(J33="Deferred",0.2,0)))))) -> 0.8 | L33: 1 | M33: Stop criteria | N33: Criteria are measurable and linked to decision authority. | O33: Pilot Definition / Stage 0-1 Gates | P33: Stage 0 Gate | Q33: W2
A34: FND-030 | B34: 0 | C34: Stakeholders | D34: Complete stakeholder map and RACI | E34: Assign accountability for charter, legal, architecture, security, worker consultation, pilot and review. | F34: Programme Lead | G34: All leads | H34: FND-002,FND-003 | I34: High | J34: Draft Complete | K34: =IF(J34="Completed",1,IF(J34="Draft Complete",0.8,IF(J34="In Review",0.6,IF(J34="Requires Owner Input",0.3,IF(J34="Blocked",0.1,IF(J34="Deferred",0.2,0)))))) -> 0.8 | L34: 1.5 | M34: RACI matrix | N34: Every mandatory foundation deliverable has one accountable role. | O34: Stakeholder RACI sheet | P34: Stage 0 Gate | Q34: W1 | R34: Names pending.
A35: FND-031 | B35: 0 | C35: Security | D35: Complete foundation threat model | E35: Identify system, privacy, employment, endpoint, insider and AI-specific threats before design is approved. | F35: CISO/Security Architect | G35: DPO/Desktop/AI | H35: FND-011 | I35: Critical | J35: Draft Complete | K35: =IF(J35="Completed",1,IF(J35="Draft Complete",0.8,IF(J35="In Review",0.6,IF(J35="Requires Owner Input",0.3,IF(J35="Blocked",0.1,IF(J35="Deferred",0.2,0)))))) -> 0.8 | L35: 3 | M35: Foundation threat register | N35: Threats have likelihood, impact, control, owner and validation plan. | O35: Foundation Threats sheet | P35: Stage 0 Gate | Q35: W2 | R35: Security review pending.
A36: FND-032 | B36: 0 | C36: Pilot ethics | D36: Define participant protection | E36: Specify voluntary/appropriate participation model, no adverse action from pilot output, employee access and direct support. | F36: HR/DPO | G36: Executive Sponsor/Product | H36: FND-009,FND-018 | I36: Critical | J36: Draft Complete | K36: =IF(J36="Completed",1,IF(J36="Draft Complete",0.8,IF(J36="In Review",0.6,IF(J36="Requires Owner Input",0.3,IF(J36="Blocked",0.1,IF(J36="Deferred",0.2,0)))))) -> 0.8 | L36: 1.5 | M36: Participant protection rules | N36: Pilot participants receive notice, support, challenge rights and no automated adverse decisions. | O36: Pilot Definition sheet | P36: Stage 0 Gate | Q36: W2
A37: FND-033 | B37: 0 | C37: Review | D37: Run Stage 0 cross-functional review | E37: Review charter, purpose matrix, DPIA pack, legal questions, threat model, consultation and pilot. | F37: Programme Lead | G37: CEO/CTO/DPO/Legal/CISO/HR/Employee Rep | H37: FND-004:FND-032 | I37: Critical | J37: Not Started | K37: =IF(J37="Completed",1,IF(J37="Draft Complete",0.8,IF(J37="In Review",0.6,IF(J37="Requires Owner Input",0.3,IF(J37="Blocked",0.1,IF(J37="Deferred",0.2,0)))))) -> 0 | L37: 2 | M37: Review minutes and actions | N37: All mandatory objections and conditions are recorded. | O37: Stage 0-1 Gates | P37: Stage 0 Gate | Q37: W2
A38: FND-034 | B38: 0 | C38: Gate | D38: Record Stage 0 decision | E38: Approve, conditionally approve, hold or reject entry into implementation planning. | F38: Executive Sponsor | G38: DPO/Legal/CISO/CTO/HR | H38: FND-033 | I38: Critical | J38: Not Started | K38: =IF(J38="Completed",1,IF(J38="Draft Complete",0.8,IF(J38="In Review",0.6,IF(J38="Requires Owner Input",0.3,IF(J38="Blocked",0.1,IF(J38="Deferred",0.2,0)))))) -> 0 | L38: 0.5 | M38: Stage 0 gate decision | N38: Decision authority, conditions, dates and evidence are recorded. | O38: Stage 0-1 Gates | P38: Stage 0 Gate | Q38: W2
A39: FND-035 | B39: 1 | C39: Market validation | D39: Define market-category taxonomy | E39: Separate employee monitoring, task mining, process intelligence, skills intelligence, developer intelligence, record/replay and AI observability. | F39: Product Strategy | G39: Research/Architecture | H39: FND-004 | I39: High | J39: Completed | K39: =IF(J39="Completed",1,IF(J39="Draft Complete",0.8,IF(J39="In Review",0.6,IF(J39="Requires Owner Input",0.3,IF(J39="Blocked",0.1,IF(J39="Deferred",0.2,0)))))) -> 1 | L39: 1 | M39: Category taxonomy | N39: Competitors are compared within the correct category. | O39: Market Landscape sheet | P39: Stage 1 Gate | Q39: W1
A40: FND-036 | B40: 1 | C40: Market validation | D40: Research employee monitoring category | E40: Document market baseline for screen, keystrokes, app/web, idle, privacy controls and reporting. | F40: Product Strategy | G40: Legal/Security | H40: FND-035 | I40: High | J40: Completed | K40: =IF(J40="Completed",1,IF(J40="Draft Complete",0.8,IF(J40="In Review",0.6,IF(J40="Requires Owner Input",0.3,IF(J40="Blocked",0.1,IF(J40="Deferred",0.2,0)))))) -> 1 | L40: 1.5 | M40: Monitoring competitor analysis | N40: Capabilities, positioning and limits are source-backed. | O40: Teramind / ActivTrak sources | P40: Stage 1 Gate | Q40: W1
A41: FND-037 | B41: 1 | C41: Market validation | D41: Research task/process mining | E41: Document action capture, workflow discovery, process variants and automation positioning. | F41: Product Strategy | G41: Operations/AI | H41: FND-035 | I41: High | J41: Completed | K41: =IF(J41="Completed",1,IF(J41="Draft Complete",0.8,IF(J41="In Review",0.6,IF(J41="Requires Owner Input",0.3,IF(J41="Blocked",0.1,IF(J41="Deferred",0.2,0)))))) -> 1 | L41: 1.5 | M41: Task-mining analysis | N41: UiPath, ABBYY, Soroco and Workfellow are compared. | O41: Market Landscape / Source Register | P41: Stage 1 Gate | Q41: W1
A42: FND-038 | B42: 1 | C42: Market validation | D42: Research skills intelligence and learning | E42: Compare inferred skills, evidence, employee review, learning plans and role readiness. | F42: Product/HR/L&D | G42: AI/Data | H42: FND-035 | I42: High | J42: Completed | K42: =IF(J42="Completed",1,IF(J42="Draft Complete",0.8,IF(J42="In Review",0.6,IF(J42="Requires Owner Input",0.3,IF(J42="Blocked",0.1,IF(J42="Deferred",0.2,0)))))) -> 1 | L42: 1.5 | M42: Skills-intelligence analysis | N42: Skills platforms and Nessovo differentiation are recorded. | O42: Market Landscape / Source Register | P42: Stage 1 Gate | Q42: W1
A43: FND-039 | B43: 1 | C43: Market validation | D43: Research developer and AI-work intelligence | E43: Compare engineering metrics, AI usage, code attribution, review, delivery and coaching. | F43: Product/CTO | G43: Engineering/AI | H43: FND-035 | I43: High | J43: Completed | K43: =IF(J43="Completed",1,IF(J43="Draft Complete",0.8,IF(J43="In Review",0.6,IF(J43="Requires Owner Input",0.3,IF(J43="Blocked",0.1,IF(J43="Deferred",0.2,0)))))) -> 1 | L43: 1.5 | M43: Developer-intelligence analysis | N43: Relevant tools and limitations are recorded. | O43: Market Landscape / Source Register | P43: Stage 1 Gate | Q43: W1
A44: FND-040 | B44: 1 | C44: Open-source due diligence | D44: Complete GitHub reference scan | E44: Inspect Screenpipe, ActivityWatch, OpenAdapt, Claude-Mem, Task Observer, WakaTime and standards projects. | F44: Architecture/Engineering | G44: Legal/Security | H44: FND-035 | I44: Critical | J44: Completed | K44: =IF(J44="Completed",1,IF(J44="Draft Complete",0.8,IF(J44="In Review",0.6,IF(J44="Requires Owner Input",0.3,IF(J44="Blocked",0.1,IF(J44="Deferred",0.2,0)))))) -> 1 | L44: 3 | M44: GitHub OSS scan | N44: Each project has maturity, relevance, licence and reuse recommendation. | O44: GitHub OSS Scan sheet | P44: Stage 1 Gate | Q44: W1
A45: FND-041 | B45: 1 | C45: Open-source due diligence | D45: Verify initial licence posture | E45: Record commercial-use constraints and identify items needing legal licence review. | F45: Legal/Architecture | G45: Procurement/Product | H45: FND-040 | I45: Critical | J45: Draft Complete | K45: =IF(J45="Completed",1,IF(J45="Draft Complete",0.8,IF(J45="In Review",0.6,IF(J45="Requires Owner Input",0.3,IF(J45="Blocked",0.1,IF(J45="Deferred",0.2,0)))))) -> 0.8 | L45: 2 | M45: Licence register draft | N45: No project is recommended for incorporation without a recorded licence decision. | O45: GitHub OSS Scan / repository licences | P45: Stage 1 Gate | Q45: W1 | R45: Formal legal opinion pending.
A46: FND-042 | B46: 1 | C46: Strategy | D46: Complete market gap matrix | E46: Compare capture, task assurance, provenance, capability, coaching, training, self-improvement and governance. | F46: Product Strategy | G46: Architecture/HR/AI | H46: FND-036:FND-041 | I46: Critical | J46: Draft Complete | K46: =IF(J46="Completed",1,IF(J46="Draft Complete",0.8,IF(J46="In Review",0.6,IF(J46="Requires Owner Input",0.3,IF(J46="Blocked",0.1,IF(J46="Deferred",0.2,0)))))) -> 0.8 | L46: 2 | M46: Gap matrix | N46: Differentiation is stated as a capability combination, not unsupported novelty. | O46: Gap Matrix sheet | P46: Stage 1 Gate | Q46: W1
A47: FND-043 | B47: 1 | C47: Strategy | D47: Approve strategic differentiation | E47: Define the proprietary core: evidence graph, task assurance, capability evidence, Growth Coach and Skill Forge. | F47: CEO/Product/CTO | G47: Architecture/HR | H47: FND-042 | I47: Critical | J47: Draft Complete | K47: =IF(J47="Completed",1,IF(J47="Draft Complete",0.8,IF(J47="In Review",0.6,IF(J47="Requires Owner Input",0.3,IF(J47="Blocked",0.1,IF(J47="Deferred",0.2,0)))))) -> 0.8 | L47: 1 | M47: Differentiation decision | N47: Build focus and commodity capabilities are separated. | O47: Product Charter v1 / Build Buy Decisions | P47: Stage 1 Gate | Q47: W1 | R47: Leadership review pending.
A48: FND-044 | B48: 1 | C48: Architecture | D48: Create capability-domain map | E48: Map product capabilities to HumanOS services and new bounded contexts. | F48: Enterprise Architect | G48: Product/Platform/AI | H48: FND-043 | I48: Critical | J48: Draft Complete | K48: =IF(J48="Completed",1,IF(J48="Draft Complete",0.8,IF(J48="In Review",0.6,IF(J48="Requires Owner Input",0.3,IF(J48="Blocked",0.1,IF(J48="Deferred",0.2,0)))))) -> 0.8 | L48: 2 | M48: Capability-to-service map | N48: Every capability has a system of record and integration boundary. | O48: Reference Architecture / Microservices Map | P48: Stage 1 Gate | Q48: W1
A49: FND-045 | B49: 1 | C49: Architecture | D49: Complete build/buy/integrate/defer matrix | E49: Make component-level decisions based on differentiation, risk, maturity and licence. | F49: CTO/Architecture | G49: Product/Legal/Procurement | H49: FND-040,FND-043 | I49: Critical | J49: Draft Complete | K49: =IF(J49="Completed",1,IF(J49="Draft Complete",0.8,IF(J49="In Review",0.6,IF(J49="Requires Owner Input",0.3,IF(J49="Blocked",0.1,IF(J49="Deferred",0.2,0)))))) -> 0.8 | L49: 2.5 | M49: Build Buy Decisions | N49: Each component has a recommendation, rationale, risk and revisit trigger. | O49: Build Buy Decisions sheet | P49: Stage 1 Gate | Q49: W1 | R49: Final procurement/legal review pending.
A50: FND-046 | B50: 1 | C50: Architecture | D50: Define reference architecture layers | E50: Define device edge, ingestion, evidence, intelligence, capability, coaching, governance and reporting. | F50: Enterprise Architect | G50: Security/Data/AI/Desktop | H50: FND-044 | I50: Critical | J50: Draft Complete | K50: =IF(J50="Completed",1,IF(J50="Draft Complete",0.8,IF(J50="In Review",0.6,IF(J50="Requires Owner Input",0.3,IF(J50="Blocked",0.1,IF(J50="Deferred",0.2,0)))))) -> 0.8 | L50: 3 | M50: Reference architecture | N50: Components, runtimes, data, events and HumanOS reuse are explicit. | O50: Reference Architecture sheet | P50: Stage 1 Gate | Q50: W1
A51: FND-047 | B51: 1 | C51: Architecture | D51: Set bounded contexts and deployment granularity | E51: Avoid premature splitting; identify initial deployables and future split triggers. | F51: Enterprise Architect | G51: Backend/Platform/SRE | H51: FND-046 | I51: Critical | J51: Draft Complete | K51: =IF(J51="Completed",1,IF(J51="Draft Complete",0.8,IF(J51="In Review",0.6,IF(J51="Requires Owner Input",0.3,IF(J51="Blocked",0.1,IF(J51="Deferred",0.2,0)))))) -> 0.8 | L51: 2 | M51: Service-boundary decision | N51: Each boundary has ownership, scale, security or transactional justification. | O51: Reference Architecture / ADR-012 | P51: Stage 1 Gate | Q51: W1
A52: FND-048 | B52: 1 | C52: Technology | D52: Approve Java/Python/native responsibility split | E52: Use Java for durable domain services, Python for AI/evals and native code for endpoint capture. | F52: CTO/Architecture | G52: Java/Python/Desktop Leads | H52: FND-046 | I52: Critical | J52: Draft Complete | K52: =IF(J52="Completed",1,IF(J52="Draft Complete",0.8,IF(J52="In Review",0.6,IF(J52="Requires Owner Input",0.3,IF(J52="Blocked",0.1,IF(J52="Deferred",0.2,0)))))) -> 0.8 | L52: 1.5 | M52: Runtime decision | N52: Responsibility boundaries and interface contracts are stated. | O52: Reference Architecture / ADRs | P52: Stage 1 Gate | Q52: W1
A53: FND-049 | B53: 1 | C53: Technology | D53: Assess Java and Spring baseline | E53: Retain current supported HumanOS baseline unless migration is justified; benchmark Java 25/Spring Boot 4.1 for greenfield-compatible services. | F53: Java Platform Lead | G53: Architecture/SRE/Security | H53: FND-048 | I53: High | J53: Draft Complete | K53: =IF(J53="Completed",1,IF(J53="Draft Complete",0.8,IF(J53="In Review",0.6,IF(J53="Requires Owner Input",0.3,IF(J53="Blocked",0.1,IF(J53="Deferred",0.2,0)))))) -> 0.8 | L53: 1.5 | M53: Java baseline recommendation | N53: Compatibility, support, security and migration criteria are recorded. | O53: Spring/OpenJDK sources | P53: Stage 1 Gate | Q53: W1
A54: FND-050 | B54: 1 | C54: Event architecture | D54: Define event streaming and schema strategy | E54: Use Kafka-compatible streaming, versioned contracts, idempotency and CloudEvents-style envelope. | F54: Data/Platform Architect | G54: Backend/SRE | H54: FND-046 | I54: Critical | J54: Draft Complete | K54: =IF(J54="Completed",1,IF(J54="Draft Complete",0.8,IF(J54="In Review",0.6,IF(J54="Requires Owner Input",0.3,IF(J54="Blocked",0.1,IF(J54="Deferred",0.2,0)))))) -> 0.8 | L54: 2 | M54: Event architecture decision | N54: Partitioning, ordering, retry, schema and replay principles are defined. | O54: Apache Kafka / CloudEvents | P54: Stage 1 Gate | Q54: W1
A55: FND-051 | B55: 1 | C55: Policy and observability | D55: Define OPA and OpenTelemetry usage | E55: Use policy-as-code where it adds value; keep evidence content out of operational traces by default. | F55: Security/Platform Architect | G55: SRE/AI/DPO | H55: FND-046 | I55: High | J55: Draft Complete | K55: =IF(J55="Completed",1,IF(J55="Draft Complete",0.8,IF(J55="In Review",0.6,IF(J55="Requires Owner Input",0.3,IF(J55="Blocked",0.1,IF(J55="Deferred",0.2,0)))))) -> 0.8 | L55: 2 | M55: Policy/observability design | N55: Decision and data boundaries are explicit and sensitive content is opt-in only. | O55: OPA / OpenTelemetry sources | P55: Stage 1 Gate | Q55: W1
A56: FND-052 | B56: 1 | C56: Data architecture | D56: Select initial data stores | E56: Use PostgreSQL and object storage first; add vector/search capability as justified; defer graph database until query evidence. | F56: Data Architect | G56: Backend/AI/SRE | H56: FND-046 | I56: Critical | J56: Draft Complete | K56: =IF(J56="Completed",1,IF(J56="Draft Complete",0.8,IF(J56="In Review",0.6,IF(J56="Requires Owner Input",0.3,IF(J56="Blocked",0.1,IF(J56="Deferred",0.2,0)))))) -> 0.8 | L56: 2 | M56: Data-store decision | N56: System-of-record, retention, indexing and future split triggers are stated. | O56: Reference Architecture / ADR-009 | P56: Stage 1 Gate | Q56: W1
A57: FND-053 | B57: 1 | C57: Workflow architecture | D57: Confirm HumanOS workflow-runtime reuse | E57: Use existing workflow capabilities for review, coaching, gates and skill lifecycle before adding another orchestrator. | F57: Platform Architect | G57: Workflow Team/Product | H57: FND-046 | I57: High | J57: Draft Complete | K57: =IF(J57="Completed",1,IF(J57="Draft Complete",0.8,IF(J57="In Review",0.6,IF(J57="Requires Owner Input",0.3,IF(J57="Blocked",0.1,IF(J57="Deferred",0.2,0)))))) -> 0.8 | L57: 1 | M57: Orchestration decision | N57: Known runtime gaps and trigger for alternative evaluation are documented. | O57: HumanOS architecture assumption | P57: Stage 1 Gate | Q57: W1
A58: FND-054 | B58: 1 | C58: AI architecture | D58: Define evaluator and provenance architecture | E58: Separate deterministic evidence processing from model inference; version prompts, skills, models and confidence. | F58: AI Architect | G58: Data/Product/Governance | H58: FND-046 | I58: Critical | J58: Draft Complete | K58: =IF(J58="Completed",1,IF(J58="Draft Complete",0.8,IF(J58="In Review",0.6,IF(J58="Requires Owner Input",0.3,IF(J58="Blocked",0.1,IF(J58="Deferred",0.2,0)))))) -> 0.8 | L58: 2.5 | M58: AI evaluation architecture | N58: All material findings link to evidence, model/skill version and human-review state. | O58: Reference Architecture / NIST AI RMF | P58: Stage 1 Gate | Q58: W2
A59: FND-055 | B59: 1 | C59: Device architecture | D59: Define device-agent foundation principles | E59: Separate edge agent, local policy, encrypted journal, signed batches, health, update and user-visible controls. | F59: Desktop Architect | G59: Security/Platform/DPO | H59: FND-046 | I59: Critical | J59: Draft Complete | K59: =IF(J59="Completed",1,IF(J59="Draft Complete",0.8,IF(J59="In Review",0.6,IF(J59="Requires Owner Input",0.3,IF(J59="Blocked",0.1,IF(J59="Deferred",0.2,0)))))) -> 0.8 | L59: 2.5 | M59: Device-agent architecture principles | N59: Foundation is sufficient to scope Stage 3 without implementing unsafe capture. | O59: Reference Architecture / Foundation Threats | P59: Stage 1 Gate | Q59: W2
A60: FND-056 | B60: 1 | C60: Economics | D60: Collect data-volume and usage assumptions | E60: Obtain employee count, active hours, screenshot frequency, retention, regions and AI-analysis volume. | F60: Product Finance | G60: SRE/Data/Product | H60: FND-009,FND-046 | I60: High | J60: Requires Owner Input | K60: =IF(J60="Completed",1,IF(J60="Draft Complete",0.8,IF(J60="In Review",0.6,IF(J60="Requires Owner Input",0.3,IF(J60="Blocked",0.1,IF(J60="Deferred",0.2,0)))))) -> 0.3 | L60: 1.5 | M60: Cost-model inputs | N60: Assumptions are approved and sensitivity ranges are provided. | O60: Assumptions Questions sheet | P60: Stage 1 Gate | Q60: W2
A61: FND-057 | B61: 1 | C61: Economics | D61: Produce preliminary cost model | E61: Estimate endpoint, ingestion, storage, AI inference, observability and support costs. | F61: FinOps/SRE | G61: Data/AI/Product | H61: FND-056 | I61: High | J61: Not Started | K61: =IF(J61="Completed",1,IF(J61="Draft Complete",0.8,IF(J61="In Review",0.6,IF(J61="Requires Owner Input",0.3,IF(J61="Blocked",0.1,IF(J61="Deferred",0.2,0)))))) -> 0 | L61: 2.5 | M61: Cost and sensitivity model | N61: Low/base/high pilot and scale cases are calculated. | O61: Requires usage assumptions | P61: Stage 1 Gate | Q61: W2
... A64: FND-060 | B64: 1 | C64: Technical validation | D64: Define Stage 2–3 spike backlog | E64: Specify ontology and device-agent spikes that reduce the highest uncertainty first. | F64: Programme/Architecture | G64: Product/Desktop/AI | H64: FND-046:FND-055 | I64: Critical | J64: Draft Complete | K64: =IF(J64="Completed",1,IF(J64="Draft Complete",0.8,IF(J64="In Review",0.6,IF(J64="Requires Owner Input",0.3,IF(J64="Blocked",0.1,IF(J64="Deferred",0.2,0)))))) -> 0.8 | L64: 2 | M64: Next-stage spike backlog | N64: Each spike has hypothesis, method, metric, owner and decision rule. | O64: Master Prompts / Architecture Decisions | P64: Stage 1 Gate | Q64: W2
A65: FND-061 | B65: 1 | C65: Security review | D65: Run architecture threat review | E65: Review endpoint, event, evidence, identity, model, manager-access and supply-chain risks. | F65: CISO/Security Architect | G65: DPO/Architecture/Desktop/AI | H65: FND-031,FND-046 | I65: Critical | J65: In Review | K65: =IF(J65="Completed",1,IF(J65="Draft Complete",0.8,IF(J65="In Review",0.6,IF(J65="Requires Owner Input",0.3,IF(J65="Blocked",0.1,IF(J65="Deferred",0.2,0)))))) -> 0.6 | L65: 2 | M65: Security review record | N65: Critical threats have blocking controls and verification plans. | O65: Foundation Threats | P65: Stage 1 Gate | Q65: W2 | R65: Named reviewers pending.
A66: FND-062 | B66: 1 | C66: Architecture governance | D66: Review and accept ADR set | E66: Architecture board reviews core decisions and unresolved alternatives. | F66: Architecture Board | G66: CTO/Platform/Data/AI/Security | H66: FND-046:FND-055 | I66: Critical | J66: In Review | K66: =IF(J66="Completed",1,IF(J66="Draft Complete",0.8,IF(J66="In Review",0.6,IF(J66="Requires Owner Input",0.3,IF(J66="Blocked",0.1,IF(J66="Deferred",0.2,0)))))) -> 0.6 | L66: 2 | M66: Accepted ADR register | N66: Each ADR is accepted, rejected or returned with actions. | O66: Architecture Decisions sheet | P66: Stage 1 Gate | Q66: W2
A67: FND-063 | B67: 1 | C67: Research traceability | D67: Complete source register | E67: Record official product, repository, standard, legal and prompt-engineering sources. | F67: Research Lead | G67: Product/Architecture/Legal | H67: FND-035:FND-055 | I67: High | J67: Completed | K67: =IF(J67="Completed",1,IF(J67="Draft Complete",0.8,IF(J67="In Review",0.6,IF(J67="Requires Owner Input",0.3,IF(J67="Blocked",0.1,IF(J67="Deferred",0.2,0)))))) -> 1 | L67: 1.5 | M67: Source register | N67: Every material researched claim can be traced to a URL. | O67: Source Register sheet | P67: Stage 1 Gate | Q67: W2
